Workbook

Sheet All_India_Index_Upto_April23 (1
A1: Sector | B1: Year | C1: Month | D1: Cereals and products | E1: Meat and fish | F1: Egg | G1: Milk and products | H1: Oils and fats | I1: Fruits | J1: Vegetables | K1: Pulses and products | L1: Sugar and Confectionery | M1: Spices | N1: Non-alcoholic beverages | O1: Prepared meals, snacks, sweets etc. | P1: Food and beverages | Q1: Pan, tobacco and intoxicants | R1: Clothing | S1: Footwear | T1: Clothing and footwear | U1: Housing | V1: Fuel and light | W1: Household goods and services | X1: Health | Y1: Transport and communication | Z1: Recreation and amusement | AA1: Education | AB1: Personal care and effects | AC1: Miscellaneous | AD1: General index
A2: Rural | B2: 2013 | C2: January | D2: 107.5 | E2: 106.3 | F2: 108.1 | G2: 104.9 | H2: 106.1 | I2: 103.9 | J2: 101.9 | K2: 106.1 | L2: 106.8 | M2: 103.1 | N2: 104.8 | O2: 106.7 | P2: 105.5 | Q2: 105.1 | R2: 106.5 | S2: 105.8 | T2: 106.4 | U2: NA | V2: 105.5 | W2: 104.8 | X2: 104 | Y2: 103.3 | Z2: 103.4 | AA2: 103.8 | AB2: 104.7 | AC2: 104 | AD2: 105.1
A3: Urban | B3: 2013 | C3: January | D3: 110.5 | E3: 109.1 | F3: 113 | G3: 103.6 | H3: 103.4 | I3: 102.3 | J3: 102.9 | K3: 105.8 | L3: 105.1 | M3: 101.8 | N3: 105.1 | O3: 107.9 | P3: 105.9 | Q3: 105.2 | R3: 105.9 | S3: 105 | T3: 105.8 | U3: 100.3 | V3: 105.4 | W3: 104.8 | X3: 104.1 | Y3: 103.2 | Z3: 102.9 | AA3: 103.5 | AB3: 104.3 | AC3: 103.7 | AD3: 104
A4: Rural+Urban | B4: 2013 | C4: January | D4: 108.4 | E4: 107.3 | F4: 110 | G4: 104.4 | H4: 105.1 | I4: 103.2 | J4: 102.2 | K4: 106 | L4: 106.2 | M4: 102.7 | N4: 104.9 | O4: 107.3 | P4: 105.6 | Q4: 105.1 | R4: 106.3 | S4: 105.5 | T4: 106.2 | U4: 100.3 | V4: 105.5 | W4: 104.8 | X4: 104 | Y4: 103.2 | Z4: 103.1 | AA4: 103.6 | AB4: 104.5 | AC4: 103.9 | AD4: 104.6
A5: Rural | B5: 2013 | C5: February | D5: 109.2 | E5: 108.7 | F5: 110.2 | G5: 105.4 | H5: 106.7 | I5: 104 | J5: 102.4 | K5: 105.9 | L5: 105.7 | M5: 103.1 | N5: 105.1 | O5: 107.7 | P5: 106.3 | Q5: 105.6 | R5: 107.1 | S5: 106.3 | T5: 107 | U5: NA | V5: 106.2 | W5: 105.2 | X5: 104.4 | Y5: 103.9 | Z5: 104 | AA5: 104.1 | AB5: 104.6 | AC5: 104.4 | AD5: 105.8
A6: Urban | B6: 2013 | C6: February | D6: 112.9 | E6: 112.9 | F6: 116.9 | G6: 104 | H6: 103.5 | I6: 103.1 | J6: 104.9 | K6: 104.1 | L6: 103.8 | M6: 102.3 | N6: 106 | O6: 109 | P6: 107.2 | Q6: 106 | R6: 106.6 | S6: 105.5 | T6: 106.4 | U6: 100.4 | V6: 105.7 | W6: 105.2 | X6: 104.7 | Y6: 104.4 | Z6: 103.3 | AA6: 103.7 | AB6: 104.3 | AC6: 104.3 | AD6: 104.7
A7: Rural+Urban | B7: 2013 | C7: February | D7: 110.4 | E7: 110.2 | F7: 112.8 | G7: 104.9 | H7: 105.5 | I7: 103.6 | J7: 103.2 | K7: 105.3 | L7: 105.1 | M7: 102.8 | N7: 105.5 | O7: 108.3 | P7: 106.6 | Q7: 105.7 | R7: 106.9 | S7: 106 | T7: 106.8 | U7: 100.4 | V7: 106 | W7: 105.2 | X7: 104.5 | Y7: 104.2 | Z7: 103.6 | AA7: 103.9 | AB7: 104.5 | AC7: 104.4 | AD7: 105.3
A8: Rural | B8: 2013 | C8: March | D8: 110.2 | E8: 108.8 | F8: 109.9 | G8: 105.6 | H8: 106.2 | I8: 105.7 | J8: 101.4 | K8: 105.7 | L8: 105 | M8: 103.3 | N8: 105.6 | O8: 108.2 | P8: 106.6 | Q8: 106.5 | R8: 107.6 | S8: 106.8 | T8: 107.5 | U8: NA | V8: 106.1 | W8: 105.6 | X8: 104.7 | Y8: 104.6 | Z8: 104 | AA8: 104.3 | AB8: 104.3 | AC8: 104.6 | AD8: 106
A9: Urban | B9: 2013 | C9: March | D9: 113.9 | E9: 111.4 | F9: 113.2 | G9: 104.3 | H9: 102.7 | I9: 104.9 | J9: 103.8 | K9: 103.5 | L9: 102.6 | M9: 102.4 | N9: 107 | O9: 109.8 | P9: 107.3 | Q9: 106.8 | R9: 107.2 | S9: 106 | T9: 107 | U9: 100.4 | V9: 106 | W9: 105.7 | X9: 105.2 | Y9: 105.5 | Z9: 103.5 | AA9: 103.8 | AB9: 104.2 | AC9: 104.9 | AD9: 105
A10: Rural+Urban | B10: 2013 | C10: March | D10: 111.4 | E10: 109.7 | F10: 111.2 | G10: 105.1 | H10: 104.9 | I10: 105.3 | J10: 102.2 | K10: 105 | L10: 104.2 | M10: 103 | N10: 106.2 | O10: 108.9 | P10: 106.9 | Q10: 106.6 | R10: 107.4 | S10: 106.5 | T10: 107.3 | U10: 100.4 | V10: 106.1 | W10: 105.6 | X10: 104.9 | Y10: 105.1 | Z10: 103.7 | AA10: 104 | AB10: 104.3 | AC10: 104.7 | AD10: 105.5
A11: Rural | B11: 2013 | C11: April | D11: 110.2 | E11: 109.5 | F11: 106.9 | G11: 106.3 | H11: 105.7 | I11: 108.3 | J11: 103.4 | K11: 105.7 | L11: 104.2 | M11: 103.2 | N11: 106.5 | O11: 108.8 | P11: 107.1 | Q11: 107.1 | R11: 108.1 | S11: 107.4 | T11: 108 | U11: NA | V11: 106.5 | W11: 106.1 | X11: 105.1 | Y11: 104.4 | Z11: 104.5 | AA11: 104.8 | AB11: 102.7 | AC11: 104.6 | AD11: 106.4
A12: Urban | B12: 2013 | C12: April | D12: 114.6 | E12: 113.4 | F12: 106 | G12: 104.7 | H12: 102.1 | I12: 109.5 | J12: 109.7 | K12: 104.6 | L12: 102 | M12: 103.5 | N12: 108.2 | O12: 110.6 | P12: 108.8 | Q12: 108.5 | R12: 107.9 | S12: 106.4 | T12: 107.7 | U12: 100.5 | V12: 106.4 | W12: 106.5 | X12: 105.7 | Y12: 105 | Z12: 104 | AA12: 105.2 | AB12: 103.2 | AC12: 105.1 | AD12: 105.7
A13: Rural+Urban | B13: 2013 | C13: April | D13: 111.6 | E13: 110.9 | F13: 106.6 | G13: 105.7 | H13: 104.4 | I13: 108.9 | J13: 105.5 | K13: 105.3 | L13: 103.5 | M13: 103.3 | N13: 107.2 | O13: 109.6 | P13: 107.7 | Q13: 107.5 | R13: 108 | S13: 107 | T13: 107.9 | U13: 100.5 | V13: 106.5 | W13: 106.3 | X13: 105.3 | Y13: 104.7 | Z13: 104.2 | AA13: 105 | AB13: 102.9 | AC13: 104.8 | AD13: 106.1
A14: Rural | B14: 2013 | C14: May | D14: 110.9 | E14: 109.8 | F14: 105.9 | G14: 107.5 | H14: 105.3 | I14: 108.1 | J14: 107.3 | K14: 106.1 | L14: 103.7 | M14: 104 | N14: 107.4 | O14: 109.9 | P14: 108.1 | Q14: 108.1 | R14: 108.8 | S14: 107.9 | T14: 108.6 | U14: NA | V14: 107.5 | W14: 106.8 | X14: 105.7 | Y14: 104.1 | Z14: 105 | AA14: 105.5 | AB14: 102.1 | AC14: 104.8 | AD14: 107.2
A15: Urban | B15: 2013 | C15: May | D15: 115.4 | E15: 114.2 | F15: 102.7 | G15: 105.5 | H15: 101.5 | I15: 110.6 | J15: 123.7 | K15: 105.2 | L15: 101.9 | M15: 105 | N15: 109.1 | O15: 111.3 | P15: 111.1 | Q15: 109.8 | R15: 108.5 | S15: 106.7 | T15: 108.3 | U15: 100.5 | V15: 107.2 | W15: 107.1 | X15: 106.2 | Y15: 103.9 | Z15: 104.6 | AA15: 105.7 | AB15: 102.6 | AC15: 104.9 | AD15: 106.6
A16: Rural+Urban | B16: 2013 | C16: May | D16: 112.3 | E16: 111.3 | F16: 104.7 | G16: 106.8 | H16: 103.9 | I16: 109.3 | J16: 112.9 | K16: 105.8 | L16: 103.1 | M16: 104.3 | N16: 108.1 | O16: 110.5 | P16: 109.2 | Q16: 108.6 | R16: 108.7 | S16: 107.4 | T16: 108.5 | U16: 100.5 | V16: 107.4 | W16: 106.9 | X16: 105.9 | Y16: 104 | Z16: 104.8 | AA16: 105.6 | AB16: 102.3 | AC16: 104.8 | AD16: 106.9
A17: Rural | B17: 2013 | C17: June | D17: 112.3 | E17: 112.1 | F17: 108.1 | G17: 108.3 | H17: 105.9 | I17: 109.2 | J17: 118 | K17: 106.8 | L17: 104.1 | M17: 105.4 | N17: 108.2 | O17: 111 | P17: 110.6 | Q17: 109 | R17: 109.7 | S17: 108.8 | T17: 109.5 | U17: NA | V17: 108.5 | W17: 107.5 | X17: 106.3 | Y17: 105 | Z17: 105.6 | AA17: 106.5 | AB17: 102.5 | AC17: 105.5 | AD17: 108.9
A18: Urban | B18: 2013 | C18: June | D18: 117 | E18: 120.1 | F18: 112.5 | G18: 107.3 | H18: 101.3 | I18: 112.4 | J18: 143.6 | K18: 105.4 | L18: 101.4 | M18: 106.4 | N18: 110 | O18: 112.2 | P18: 115 | Q18: 110.9 | R18: 109.2 | S18: 107.2 | T18: 108.9 | U18: 106.6 | V18: 108 | W18: 107.7 | X18: 106.5 | Y18: 105.2 | Z18: 105.2 | AA18: 108.1 | AB18: 103.3 | AC18: 106.1 | AD18: 109.7
A19: Rural+Urban | B19: 2013 | C19: June | D19: 113.8 | E19: 114.9 | F19: 109.8 | G19: 107.9 | H19: 104.2 | I19: 110.7 | J19: 126.7 | K19: 106.3 | L19: 103.2 | M19: 105.7 | N19: 109 | O19: 111.6 | P19: 112.2 | Q19: 109.5 | R19: 109.5 | S19: 108.1 | T19: 109.3 | U19: 106.6 | V19: 108.3 | W19: 107.6 | X19: 106.4 | Y19: 105.1 | Z19: 105.4 | AA19: 107.4 | AB19: 102.8 | AC19: 105.8 | AD19: 109.3
A20: Rural | B20: 2013 | C20: July | D20: 113.4 | E20: 114.9 | F20: 110.5 | G20: 109.3 | H20: 106.2 | I20: 110.3 | J20: 129.2 | K20: 107.1 | L20: 104.3 | M20: 106.4 | N20: 109.1 | O20: 112.1 | P20: 113.1 | Q20: 109.8 | R20: 110.5 | S20: 109.5 | T20: 110.3 | U20: NA | V20: 109.5 | W20: 108.3 | X20: 106.9 | Y20: 106.8 | Z20: 106.4 | AA20: 107.8 | AB20: 102.5 | AC20: 106.5 | AD20: 110.7
A21: Urban | B21: 2013 | C21: July | D21: 117.8 | E21: 119.2 | F21: 114 | G21: 108.3 | H21: 101.1 | I21: 113.2 | J21: 160.9 | K21: 105.1 | L21: 101.3 | M21: 107.5 | N21: 110.4 | O21: 113.1 | P21: 117.5 | Q21: 111.7 | R21: 109.8 | S21: 107.8 | T21: 109.5 | U21: 107.7 | V21: 108.6 | W21: 108.1 | X21: 107.1 | Y21: 107.3 | Z21: 105.9 | AA21: 110.1 | AB21: 103.2 | AC21: 107.3 | AD21: 111.4
A22: Rural+Urban | B22: 2013 | C22: July | D22: 114.8 | E22: 116.4 | F22: 111.9 | G22: 108.9 | H22: 104.3 | I22: 111.7 | J22: 140 | K22: 106.4 | L22: 103.3 | M22: 106.8 | N22: 109.6 | O22: 112.6 | P22: 114.7 | Q22: 110.3 | R22: 110.2 | S22: 108.8 | T22: 110 | U22: 107.7 | V22: 109.2 | W22: 108.2 | X22: 107 | Y22: 107.1 | Z22: 106.1 | AA22: 109.1 | AB22: 102.8 | AC22: 106.9 | AD22: 111
A23: Rural | B23: 2013 | C23: August | D23: 114.3 | E23: 115.4 | F23: 111.1 | G23: 110 | H23: 106.4 | I23: 110.8 | J23: 138.9 | K23: 107.4 | L23: 104.1 | M23: 106.9 | N23: 109.7 | O23: 112.6 | P23: 114.9 | Q23: 110.7 | R23: 111.3 | S23: 110.2 | T23: 111.1 | U23: NA | V23: 109.9 | W23: 108.7 | X23: 107.5 | Y23: 107.8 | Z23: 106.8 | AA23: 108.7 | AB23: 105 | AC23: 107.5 | AD23: 112.1
A24: Urban | B24: 2013 | C24: August | D24: 118.3 | E24: 120.4 | F24: 112.7 | G24: 108.9 | H24: 101.1 | I24: 108.7 | J24: 177 | K24: 104.7 | L24: 101 | M24: 108.5 | N24: 110.9 | O24: 114.3 | P24: 119.6 | Q24: 112.4 | R24: 110.6 | S24: 108.3 | T24: 110.2 | U24: 108.9 | V24: 109.3 | W24: 108.7 | X24: 107.6 | Y24: 108.1 | Z24: 106.5 | AA24: 110.8 | AB24: 106 | AC24: 108.3 | AD24: 112.7
A25: Rural+Urban | B25: 2013 | C25: August | D25: 115.6 | E25: 117.2 | F25: 111.7 | G25: 109.6 | H25: 104.5 | I25: 109.8 | J25: 151.8 | K25: 106.5 | L25: 103.1 | M25: 107.4 | N25: 110.2 | O25: 113.4 | P25: 116.6 | Q25: 111.2 | R25: 111 | S25: 109.4 | T25: 110.7 | U25: 108.9 | V25: 109.7 | W25: 108.7 | X25: 107.5 | Y25: 108 | Z25: 106.6 | AA25: 109.9 | AB25: 105.4 | AC25: 107.9 | AD25: 112.4
A26: Rural | B26: 2013 | C26: September | D26: 115.4 | E26: 115.7 | F26: 111.7 | G26: 111 | H26: 107.4 | I26: 110.9 | J26: 154 | K26: 108.1 | L26: 104.2 | M26: 107.9 | N26: 110.4 | O26: 114 | P26: 117.8 | Q26: 111.7 | R26: 112.7 | S26: 111.4 | T26: 112.5 | U26: NA | V26: 111.1 | W26: 109.6 | X26: 108.3 | Y26: 109.3 | Z26: 107.7 | AA26: 109.8 | AB26: 106.7 | AC26: 108.7 | AD26: 114.2
A27: Urban | B27: 2013 | C27: September | D27: 118.6 | E27: 119.1 | F27: 113.2 | G27: 109.6 | H27: 101.7 | I27: 103.2 | J27: 174.3 | K27: 105.1 | L27: 100.8 | M27: 109.1 | N27: 111.1 | O27: 115.4 | P27: 119.2 | Q27: 112.9 | R27: 111.4 | S27: 109 | T27: 111.1 | U27: 109.7 | V27: 109.5 | W27: 109.6 | X27: 107.9 | Y27: 110.4 | Z27: 107.4 | AA27: 111.2 | AB27: 106.9 | AC27: 109.4 | AD27: 113.2
A28: Rural+Urban | B28: 2013 | C28: September | D28: 116.4 | E28: 116.9 | F28: 112.3 | G28: 110.5 | H28: 105.3 | I28: 107.3 | J28: 160.9 | K28: 107.1 | L28: 103.1 | M28: 108.3 | N28: 110.7 | O28: 114.6 | P28: 118.3 | Q28: 112 | R28: 112.2 | S28: 110.4 | T28: 111.9 | U28: 109.7 | V28: 110.5 | W28: 109.6 | X28: 108.1 | Y28: 109.9 | Z28: 107.5 | AA28: 110.6 | AB28: 106.8 | AC28: 109 | AD28: 113.7
A29: Rural | B29: 2013 | C29: October | D29: 116.3 | E29: 115.4 | F29: 112.6 | G29: 111.7 | H29: 107.7 | I29: 113.2 | J29: 164.9 | K29: 108.3 | L29: 103.9 | M29: 108.2 | N29: 111.1 | O29: 114.9 | P29: 119.8 | Q29: 112.2 | R29: 113.6 | S29: 112.3 | T29: 113.4 | U29: NA | V29: 111.6 | W29: 110.4 | X29: 108.9 | Y29: 109.3 | Z29: 108.3 | AA29: 110.2 | AB29: 107.5 | AC29: 109.1 | AD29: 115.5
A30: Urban | B30: 2013 | C30: October | D30: 118.9 | E30: 118.1 | F30: 114.5 | G30: 110.4 | H30: 102.3 | I30: 106.2 | J30: 183.5 | K30: 105.3 | L30: 100.2 | M30: 109.6 | N30: 111.4 | O30: 116 | P30: 120.8 | Q30: 113.5 | R30: 112.5 | S30: 109.7 | T30: 112 | U30: 110.5 | V30: 109.7 | W30: 110.2 | X30: 108.2 | Y30: 109.7 | Z30: 108 | AA30: 111.3 | AB30: 107.3 | AC30: 109.4 | AD30: 114
A31: Rural+Urban | B31: 2013 | C31: October | D31: 117.1 | E31: 116.3 | F31: 113.3 | G31: 111.2 | H31: 105.7 | I31: 109.9 | J31: 171.2 | K31: 107.3 | L31: 102.7 | M31: 108.7 | N31: 111.2 | O31: 115.4 | P31: 120.2 | Q31: 112.5 | R31: 113.2 | S31: 111.2 | T31: 112.8 | U31: 110.5 | V31: 110.9 | W31: 110.3 | X31: 108.6 | Y31: 109.5 | Z31: 108.1 | AA31: 110.8 | AB31: 107.4 | AC31: 109.2 | AD31: 114.8
A32: Rural | B32: 2013 | C32: November | D32: 117.3 | E32: 114.9 | F32: 116.2 | G32: 112.8 | H32: 108.9 | I32: 116.6 | J32: 178.1 | K32: 109.1 | L32: 103.6 | M32: 109 | N32: 111.8 | O32: 116 | P32: 122.5 | Q32: 112.8 | R32: 114.6 | S32: 113.1 | T32: 114.4 | U32: NA | V32: 112.6 | W32: 111.3 | X32: 109.7 | Y32: 109.6 | Z32: 108.7 | AA32: 111 | AB32: 108.2 | AC32: 109.8 | AD32: 117.4
A33: Urban | B33: 2013 | C33: November | D33: 119.8 | E33: 116.3 | F33: 122.6 | G33: 112 | H33: 103.2 | I33: 110 | J33: 192.8 | K33: 106.3 | L33: 99.5 | M33: 110.3 | N33: 111.8 | O33: 117.1 | P33: 122.9 | Q33: 114.1 | R33: 113.5 | S33: 110.3 | T33: 113 | U33: 111.1 | V33: 110 | W33: 110.9 | X33: 108.6 | Y33: 109.5 | Z33: 108.5 | AA33: 111.3 | AB33: 107.9 | AC33: 109.6 | AD33: 115
A34: Rural+Urban | B34: 2013 | C34: November | D34: 118.1 | E34: 115.4 | F34: 118.7 | G34: 112.5 | H34: 106.8 | I34: 113.5 | J34: 183.1 | K34: 108.2 | L34: 102.2 | M34: 109.4 | N34: 111.8 | O34: 116.5 | P34: 122.6 | Q34: 113.1 | R34: 114.2 | S34: 111.9 | T34: 113.8 | U34: 111.1 | V34: 111.6 | W34: 111.1 | X34: 109.3 | Y34: 109.5 | Z34: 108.6 | AA34: 111.2 | AB34: 108.1 | AC34: 109.7 | AD34: 116.3
A35: Rural | B35: 2013 | C35: December | D35: 118.4 | E35: 115.9 | F35: 120.4 | G35: 113.8 | H35: 109.5 | I35: 115.5 | J35: 145.7 | K35: 109.5 | L35: 102.9 | M35: 109.8 | N35: 112.1 | O35: 116.8 | P35: 118.7 | Q35: 113.6 | R35: 115.8 | S35: 114 | T35: 115.5 | U35: NA | V35: 112.8 | W35: 112.1 | X35: 110.1 | Y35: 109.9 | Z35: 109.2 | AA35: 111.6 | AB35: 108.1 | AC35: 110.1 | AD35: 115.5
A36: Urban | B36: 2013 | C36: December | D36: 120.5 | E36: 118.1 | F36: 128.5 | G36: 112.8 | H36: 103.4 | I36: 110.7 | J36: 144.8 | K36: 107.1 | L36: 98.6 | M36: 111.9 | N36: 112.1 | O36: 118.1 | P36: 117.8 | Q36: 115 | R36: 114.2 | S36: 110.9 | T36: 113.7 | U36: 110.7 | V36: 110.4 | W36: 111.3 | X36: 109 | Y36: 109.7 | Z36: 108.9 | AA36: 111.4 | AB36: 107.7 | AC36: 109.8 | AD36: 113.3
A37: Rural+Urban | B37: 2013 | C37: December | D37: 119.1 | E37: 116.7 | F37: 123.5 | G37: 113.4 | H37: 107.3 | I37: 113.3 | J37: 145.4 | K37: 108.7 | L37: 101.5 | M37: 110.5 | N37: 112.1 | O37: 117.4 | P37: 118.4 | Q37: 114 | R37: 115.2 | S37: 112.7 | T37: 114.8 | U37: 110.7 | V37: 111.9 | W37: 111.7 | X37: 109.7 | Y37: 109.8 | Z37: 109 | AA37: 111.5 | AB37: 107.9 | AC37: 110 | AD37: 114.5
A38: Rural | B38: 2014 | C38: January | D38: 118.9 | E38: 117.1 | F38: 120.5 | G38: 114.4 | H38: 109 | I38: 115.5 | J38: 123.9 | K38: 109.6 | L38: 101.8 | M38: 110.2 | N38: 112.4 | O38: 117.3 | P38: 116 | Q38: 114 | R38: 116.5 | S38: 114.5 | T38: 116.2 | U38: NA | V38: 113 | W38: 112.6 | X38: 110.6 | Y38: 110.5 | Z38: 109.6 | AA38: 111.8 | AB38: 108.3 | AC38: 110.6 | AD38: 114.2
A39: Urban | B39: 2014 | C39: January | D39: 121.2 | E39: 122 | F39: 129.9 | G39: 113.6 | H39: 102.9 | I39: 112.1 | J39: 118.9 | K39: 107.5 | L39: 96.9 | M39: 112.7 | N39: 112.1 | O39: 119 | P39: 115.5 | Q39: 115.7 | R39: 114.8 | S39: 111.3 | T39: 114.3 | U39: 111.6 | V39: 111 | W39: 111.9 | X39: 109.7 | Y39: 110.8 | Z39: 109.8 | AA39: 111.5 | AB39: 108 | AC39: 110.5 | AD39: 112.9
A40: Rural+Urban | B40: 2014 | C40: January | D40: 119.6 | E40: 118.8 | F40: 124.1 | G40: 114.1 | H40: 106.8 | I40: 113.9 | J40: 122.2 | K40: 108.9 | L40: 100.2 | M40: 111 | N40: 112.3 | O40: 118.1 | P40: 115.8 | Q40: 114.5 | R40: 115.8 | S40: 113.2 | T40: 115.4 | U40: 111.6 | V40: 112.2 | W40: 112.3 | X40: 110.3 | Y40: 110.7 | Z40: 109.7 | AA40: 111.6 | AB40: 108.2 | AC40: 110.6 | AD40: 113.6
A41: Rural | B41: 2014 | C41: February | D41: 119.4 | E41: 117.7 | F41: 121.2 | G41: 115 | H41: 109 | I41: 116.6 | J41: 116 | K41: 109.8 | L41: 101.1 | M41: 110.4 | N41: 112.9 | O41: 117.8 | P41: 115.3 | Q41: 114.2 | R41: 117.1 | S41: 114.5 | T41: 116.7 | U41: NA | V41: 113.2 | W41: 112.9 | X41: 110.9 | Y41: 110.8 | Z41: 109.9 | AA41: 112 | AB41: 108.7 | AC41: 110.9 | AD41: 114
A42: Urban | B42: 2014 | C42: February | D42: 121.9 | E42: 122 | F42: 124.5 | G42: 115.2 | H42: 102.5 | I42: 114.1 | J42: 111.5 | K42: 108.2 | L42: 95.4 | M42: 113.5 | N42: 112.1 | O42: 119.9 | P42: 115.2 | Q42: 116.2 | R42: 115.3 | S42: 111.7 | T42: 114.7 | U42: 112.5 | V42: 111.1 | W42: 112.6 | X42: 110.4 | Y42: 111.3 | Z42: 110.3 | AA42: 111.6 | AB42: 108.7 | AC42: 111 | AD42: 113.1
A43: Rural+Urban | B43: 2014 | C43: February | D43: 120.2 | E43: 119.2 | F43: 122.5 | G43: 115.1 | H43: 106.6 | I43: 115.4 | J43: 114.5 | K43: 109.3 | L43: 99.2 | M43: 111.4 | N43: 112.6 | O43: 118.8 | P43: 115.3 | Q43: 114.7 | R43: 116.4 | S43: 113.3 | T43: 115.9 | U43: 112.5 | V43: 112.4 | W43: 112.8 | X43: 110.7 | Y43: 111.1 | Z43: 110.1 | AA43: 111.8 | AB43: 108.7 | AC43: 110.9 | AD43: 113.6
A44: Rural | B44: 2014 | C44: March | D44: 120.1 | E44: 118.1 | F44: 120.7 | G44: 116.1 | H44: 109.3 | I44: 119.6 | J44: 117.9 | K44: 110.2 | L44: 101.2 | M44: 110.7 | N44: 113 | O44: 118.3 | P44: 116.2 | Q44: 114.6 | R44: 117.5 | S44: 114.9 | T44: 117.2 | U44: NA | V44: 113.4 | W44: 113.4 | X44: 111.4 | Y44: 111.2 | Z44: 110.2 | AA44: 112.4 | AB44: 108.9 | AC44: 111.3 | AD44: 114.6
A45: Urban | B45: 2014 | C45: March | D45: 122.1 | E45: 121.4 | F45: 121.5 | G45: 116.2 | H45: 102.8 | I45: 117.7 | J45: 113.3 | K45: 108.9 | L45: 96.3 | M45: 114.1 | N45: 112.2 | O45: 120.5 | P45: 116 | Q45: 116.7 | R45: 115.8 | S45: 112.1 | T45: 115.2 | U45: 113.2 | V45: 110.9 | W45: 113 | X45: 110.8 | Y45: 111.6 | Z45: 110.9 | AA45: 111.8 | AB45: 109.2 | AC45: 111.4 | AD45: 113.7
A46: Rural+Urban | B46: 2014 | C46: Marcrh | D46: 120.7 | E46: 119.3 | F46: 121 | G46: 116.1 | H46: 106.9 | I46: 118.7 | J46: 116.3 | K46: 109.8 | L46: 99.6 | M46: 111.8 | N46: 112.7 | O46: 119.3 | P46: 116.1 | Q46: 115.2 | R46: 116.8 | S46: 113.7 | T46: 116.4 | U46: 113.2 | V46: 112.5 | W46: 113.2 | X46: 111.2 | Y46: 111.4 | Z46: 110.6 | AA46: 112 | AB46: 109 | AC46: 111.3 | AD46: 114.2
A47: Rural | B47: 2014 | C47: April | D47: 120.2 | E47: 118.9 | F47: 118.1 | G47: 117 | H47: 109.7 | I47: 125.5 | J47: 120.5 | K47: 111 | L47: 102.6 | M47: 111.2 | N47: 113.5 | O47: 118.7 | P47: 117.2 | Q47: 115.4 | R47: 118.1 | S47: 116.1 | T47: 117.8 | U47: NA | V47: 113.4 | W47: 113.7 | X47: 111.8 | Y47: 111.2 | Z47: 110.5 | AA47: 113 | AB47: 108.9 | AC47: 111.5 | AD47: 115.4
A48: Urban | B48: 2014 | C48: April | D48: 122.5 | E48: 121.7 | F48: 113.3 | G48: 117 | H48: 103.1 | I48: 126.7 | J48: 121.2 | K48: 111 | L48: 100.3 | M48: 115.3 | N48: 112.7 | O48: 121 | P48: 118.2 | Q48: 117.6 | R48: 116.3 | S48: 112.5 | T48: 115.7 | U48: 113.9 | V48: 110.9 | W48: 113.4 | X48: 111 | Y48: 111.2 | Z48: 111.2 | AA48: 112.5 | AB48: 109.1 | AC48: 111.4 | AD48: 114.7
A49: Rural+Urban | B49: 2014 | C49: April | D49: 120.9 | E49: 119.9 | F49: 116.2 | G49: 117 | H49: 107.3 | I49: 126.1 | J49: 120.7 | K49: 111 | L49: 101.8 | M49: 112.6 | N49: 113.2 | O49: 119.8 | P49: 117.6 | Q49: 116 | R49: 117.4 | S49: 114.6 | T49: 117 | U49: 113.9 | V49: 112.5 | W49: 113.6 | X49: 111.5 | Y49: 111.2 | Z49: 110.9 | AA49: 112.7 | AB49: 109 | AC49: 111.5 | AD49: 115.1
A50: Rural | B50: 2014 | C50: May | D50: 120.3 | E50: 120.2 | F50: 116.9 | G50: 118 | H50: 110.1 | I50: 126.3 | J50: 123.9 | K50: 111.5 | L50: 103.5 | M50: 111.6 | N50: 114.2 | O50: 119.2 | P50: 118.2 | Q50: 116.3 | R50: 118.7 | S50: 116.8 | T50: 118.5 | U50: NA | V50: 113.4 | W50: 114.1 | X50: 112.1 | Y50: 111.4 | Z50: 110.9 | AA50: 113.1 | AB50: 108.9 | AC50: 111.8 | AD50: 116
A51: Urban | B51: 2014 | C51: May | D51: 122.7 | E51: 124.1 | F51: 114.2 | G51: 119.1 | H51: 103.5 | I51: 129.2 | J51: 127 | K51: 112.6 | L51: 101.3 | M51: 117 | N51: 112.9 | O51: 121.7 | P51: 120 | Q51: 118.3 | R51: 116.8 | S51: 112.9 | T51: 116.2 | U51: 114.3 | V51: 111.1 | W51: 114.1 | X51: 111.2 | Y51: 111.3 | Z51: 111.5 | AA51: 112.9 | AB51: 109.3 | AC51: 111.7 | AD51: 115.6
A52: Rural+Urban | B52: 2014 | C52: May | D52: 121.1 | E52: 121.6 | F52: 115.9 | G52: 118.4 | H52: 107.7 | I52: 127.7 | J52: 125 | K52: 111.9 | L52: 102.8 | M52: 113.4 | N52: 113.7 | O52: 120.4 | P52: 118.9 | Q52: 116.8 | R52: 118 | S52: 115.2 | T52: 117.6 | U52: 114.3 | V52: 112.5 | W52: 114.1 | X52: 111.8 | Y52: 111.3 | Z52: 111.2 | AA52: 113 | AB52: 109.1 | AC52: 111.8 | AD52: 115.8
A53: Rural | B53: 2014 | C53: June | D53: 120.7 | E53: 121.6 | F53: 116.1 | G53: 119.3 | H53: 110.3 | I53: 125.8 | J53: 129.3 | K53: 112.2 | L53: 103.6 | M53: 112.3 | N53: 114.9 | O53: 120.1 | P53: 119.5 | Q53: 117.3 | R53: 119.7 | S53: 117.3 | T53: 119.3 | U53: NA | V53: 114.4 | W53: 114.9 | X53: 112.8 | Y53: 112.2 | Z53: 111.4 | AA53: 114.3 | AB53: 108 | AC53: 112.3 | AD53: 117
A54: Urban | B54: 2014 | C54: June | D54: 123.1 | E54: 125.9 | F54: 115.4 | G54: 120.4 | H54: 103.4 | I54: 131.2 | J54: 137.5 | K54: 112.8 | L54: 101.4 | M54: 118.3 | N54: 113.2 | O54: 122.4 | P54: 122 | Q54: 119 | R54: 117.4 | S54: 113.2 | T54: 116.7 | U54: 113.9 | V54: 111.2 | W54: 114.3 | X54: 111.4 | Y54: 111.5 | Z54: 111.8 | AA54: 115.1 | AB54: 108.7 | AC54: 112.2 | AD54: 116.4
A55: Rural+Urban | B55: 2014 | C55: June | D55: 121.5 | E55: 123.1 | F55: 115.8 | G55: 119.7 | H55: 107.8 | I55: 128.3 | J55: 132.1 | K55: 112.4 | L55: 102.9 | M55: 114.3 | N55: 114.2 | O55: 121.2 | P55: 120.4 | Q55: 117.8 | R55: 118.8 | S55: 115.6 | T55: 118.3 | U55: 113.9 | V55: 113.2 | W55: 114.6 | X55: 112.3 | Y55: 111.8 | Z55: 111.6 | AA55: 114.8 | AB55: 108.3 | AC55: 112.3 | AD55: 116.7
A56: Rural | B56: 2014 | C56: July | D56: 121.7 | E56: 122.5 | F56: 117.7 | G56: 120.6 | H56: 110.4 | I56: 129.1 | J56: 150.1 | K56: 113.2 | L56: 104.8 | M56: 113.3 | N56: 115.6 | O56: 120.9 | P56: 123.3 | Q56: 118 | R56: 120.7 | S56: 118.3 | T56: 120.3 | U56: NA | V56: 115.3 | W56: 115.4 | X56: 113.4 | Y56: 113.2 | Z56: 111.8 | AA56: 115.5 | AB56: 108.8 | AC56: 113.1 | AD56: 119.5
A57: Urban | B57: 2014 | C57: July | D57: 123.8 | E57: 126.4 | F57: 118 | G57: 121.6 | H57: 103.5 | I57: 133.7 | J57: 172.4 | K57: 113.1 | L57: 102.7 | M57: 120 | N57: 113.8 | O57: 123.4 | P57: 127.1 | Q57: 121 | R57: 118 | S57: 113.6 | T57: 117.4 | U57: 114.8 | V57: 111.6 | W57: 114.9 | X57: 111.5 | Y57: 113 | Z57: 112.4 | AA57: 117.8 | AB57: 109.7 | AC57: 113.5 | AD57: 118.9
A58: Rural+Urban | B58: 2014 | C58: July | D58: 122.4 | E58: 123.9 | F58: 117.8 | G58: 121 | H58: 107.9 | I58: 131.2 | J58: 157.7 | K58: 113.2 | L58: 104.1 | M58: 115.5 | N58: 114.8 | O58: 122.1 | P58: 124.7 | Q58: 118.8 | R58: 119.6 | S58: 116.3 | T58: 119.1 | U58: 114.8 | V58: 113.9 | W58: 115.2 | X58: 112.7 | Y58: 113.1 | Z58: 112.1 | AA58: 116.8 | AB58: 109.2 | AC58: 113.3 | AD58: 119.2
A59: Rural | B59: 2014 | C59: August | D59: 121.8 | E59: 122.8 | F59: 117.8 | G59: 121.9 | H59: 110.6 | I59: 129.7 | J59: 161.1 | K59: 114.1 | L59: 105.1 | M59: 114.6 | N59: 115.8 | O59: 121.7 | P59: 125.3 | Q59: 118.8 | R59: 120.9 | S59: 118.8 | T59: 120.7 | U59: NA | V59: 115.4 | W59: 115.9 | X59: 114 | Y59: 113.2 | Z59: 112.2 | AA59: 116.2 | AB59: 109.4 | AC59: 113.5 | AD59: 120.7
A60: Urban | B60: 2014 | C60: August | D60: 124.8 | E60: 127.3 | F60: 116.5 | G60: 122.2 | H60: 103.6 | I60: 132.7 | J60: 181.9 | K60: 115.2 | L60: 102.7 | M60: 122.1 | N60: 114.4 | O60: 124.7 | P60: 128.9 | Q60: 123 | R60: 118.6 | S60: 114.1 | T60: 117.9 | U60: 115.5 | V60: 111.8 | W60: 115.3 | X60: 112.2 | Y60: 112.5 | Z60: 112.9 | AA60: 119.2 | AB60: 110.5 | AC60: 113.9 | AD60: 119.9
A61: Rural+Urban | B61: 2014 | C61: August | D61: 122.7 | E61: 124.4 | F61: 117.3 | G61: 122 | H61: 108 | I61: 131.1 | J61: 168.2 | K61: 114.5 | L61: 104.3 | M61: 117.1 | N61: 115.2 | O61: 123.1 | P61: 126.6 | Q61: 119.9 | R61: 120 | S61: 116.8 | T61: 119.6 | U61: 115.5 | V61: 114 | W61: 115.6 | X61: 113.3 | Y61: 112.8 | Z61: 112.6 | AA61: 118 | AB61: 109.9 | AC61: 113.7 | AD61: 120.3
A62: Rural | B62: 2014 | C62: September | D62: 122.3 | E62: 122.4 | F62: 117.8 | G62: 122.7 | H62: 110.4 | I62: 129.8 | J62: 158.8 | K62: 115 | L62: 104.7 | M62: 114.9 | N62: 116.5 | O62: 122.6 | P62: 125.3 | Q62: 119.5 | R62: 121.7 | S62: 119.2 | T62: 121.3 | U62: NA | V62: 115.8 | W62: 116.7 | X62: 114.5 | Y62: 112.8 | Z62: 112.6 | AA62: 116.6 | AB62: 109.1 | AC62: 113.7 | AD62: 120.9
A63: Urban | B63: 2014 | C63: September | D63: 124.2 | E63: 125.4 | F63: 116.4 | G63: 122.7 | H63: 103.5 | I63: 124.5 | J63: 168.6 | K63: 116.9 | L63: 101.9 | M63: 122.9 | N63: 114.8 | O63: 125.2 | P63: 126.7 | Q63: 124.3 | R63: 119.2 | S63: 114.5 | T63: 118.4 | U63: 116.1 | V63: 111.8 | W63: 115.5 | X63: 112.3 | Y63: 111.2 | Z63: 113.4 | AA63: 120 | AB63: 110 | AC63: 113.6 | AD63: 119.2
A64: Rural+Urban | B64: 2014 | C64: September | D64: 122.9 | E64: 123.5 | F64: 117.3 | G64: 122.7 | H64: 107.9 | I64: 127.3 | J64: 162.1 | K64: 115.6 | L64: 103.8 | M64: 117.6 | N64: 115.8 | O64: 123.8 | P64: 125.8 | Q64: 120.8 | R64: 120.7 | S64: 117.2 | T64: 120.1 | U64: 116.1 | V64: 114.3 | W64: 116.1 | X64: 113.7 | Y64: 112 | Z64: 113.1 | AA64: 118.6 | AB64: 109.5 | AC64: 113.7 | AD64: 120.1
A65: Rural | B65: 2014 | C65: October | D65: 122.6 | E65: 122.5 | F65: 118.3 | G65: 123.2 | H65: 110.5 | I65: 128.9 | J65: 155.3 | K65: 115.5 | L65: 104 | M65: 115.3 | N65: 116.8 | O65: 123.2 | P65: 125.1 | Q65: 120 | R65: 122.7 | S65: 120.3 | T65: 122.3 | U65: NA | V65: 116.4 | W65: 117.5 | X65: 115.3 | Y65: 112.6 | Z65: 113 | AA65: 116.9 | AB65: 109.3 | AC65: 114 | AD65: 121
A66: Urban | B66: 2014 | C66: October | D66: 124.6 | E66: 126.1 | F66: 117.8 | G66: 123.1 | H66: 103.5 | I66: 123.5 | J66: 159.6 | K66: 117.4 | L66: 101.2 | M66: 123.8 | N66: 115.2 | O66: 125.9 | P66: 125.8 | Q66: 124.3 | R66: 119.6 | S66: 114.9 | T66: 118.9 | U66: 116.7 | V66: 112 | W66: 115.8 | X66: 112.6 | Y66: 111 | Z66: 113.6 | AA66: 120.2 | AB66: 110.1 | AC66: 113.7 | AD66: 119.1
A67: Rural+Urban | B67: 2014 | C67: October | D67: 123.2 | E67: 123.8 | F67: 118.1 | G67: 123.2 | H67: 107.9 | I67: 126.4 | J67: 156.8 | K67: 116.1 | L67: 103.1 | M67: 118.1 | N67: 116.1 | O67: 124.5 | P67: 125.4 | Q67: 121.1 | R67: 121.5 | S67: 118.1 | T67: 121 | U67: 116.7 | V67: 114.7 | W67: 116.7 | X67: 114.3 | Y67: 111.8 | Z67: 113.3 | AA67: 118.8 | AB67: 109.6 | AC67: 113.9 | AD67: 120.1
A68: Rural | B68: 2014 | C68: November | D68: 122.7 | E68: 122.6 | F68: 119.9 | G68: 124 | H68: 110.5 | I68: 128.8 | J68: 152 | K68: 116.2 | L68: 103.3 | M68: 115.8 | N68: 116.8 | O68: 124.5 | P68: 124.9 | Q68: 120.8 | R68: 123.3 | S68: 120.5 | T68: 122.9 | U68: NA | V68: 117.3 | W68: 118.1 | X68: 115.9 | Y68: 112 | Z68: 113.3 | AA68: 117.2 | AB68: 108.8 | AC68: 114.1 | AD68: 121.1
A69: Urban | B69: 2014 | C69: November | D69: 124.5 | E69: 125.6 | F69: 122.7 | G69: 124.6 | H69: 103.2 | I69: 122.2 | J69: 153.2 | K69: 119.3 | L69: 99.8 | M69: 124.6 | N69: 115.8 | O69: 126.9 | P69: 125.4 | Q69: 125.8 | R69: 120.3 | S69: 115.4 | T69: 119.5 | U69: 117.1 | V69: 112.6 | W69: 116.4 | X69: 113 | Y69: 109.7 | Z69: 114 | AA69: 120.3 | AB69: 109.6 | AC69: 113.4 | AD69: 119
A70: Rural+Urban | B70: 2014 | C70: November | D70: 123.3 | E70: 123.7 | F70: 121 | G70: 124.2 | H70: 107.8 | I70: 125.7 | J70: 152.4 | K70: 117.2 | L70: 102.1 | M70: 118.7 | N70: 116.4 | O70: 125.6 | P70: 125.1 | Q70: 122.1 | R70: 122.1 | S70: 118.4 | T70: 121.6 | U70: 117.1 | V70: 115.5 | W70: 117.3 | X70: 114.8 | Y70: 110.8 | Z70: 113.7 | AA70: 119 | AB70: 109.1 | AC70: 113.8 | AD70: 120.1
A71: Rural | B71: 2014 | C71: December | D71: 122.4 | E71: 122.4 | F71: 121.8 | G71: 124.2 | H71: 110.2 | I71: 128.6 | J71: 140.3 | K71: 116.3 | L71: 102 | M71: 116 | N71: 117.3 | O71: 124.8 | P71: 123.3 | Q71: 121.7 | R71: 123.8 | S71: 120.6 | T71: 123.3 | U71: NA | V71: 117.4 | W71: 118.2 | X71: 116.2 | Y71: 111.5 | Z71: 113.3 | AA71: 117.7 | AB71: 109.4 | AC71: 114.2 | AD71: 120.3
A72: Urban | B72: 2014 | C72: December | D72: 124 | E72: 124.7 | F72: 126.3 | G72: 124.9 | H72: 103 | I72: 122.3 | J72: 141 | K72: 120.1 | L72: 97.8 | M72: 125.4 | N72: 116.1 | O72: 127.6 | P72: 124 | Q72: 126.4 | R72: 120.7 | S72: 115.8 | T72: 120 | U72: 116.5 | V72: 113 | W72: 116.8 | X72: 113.2 | Y72: 108.8 | Z72: 114.3 | AA72: 120.7 | AB72: 110.4 | AC72: 113.4 | AD72: 118.4
A73: Rural+Urban | B73: 2014 | C73: December | D73: 122.9 | E73: 123.2 | F73: 123.5 | G73: 124.5 | H73: 107.6 | I73: 125.7 | J73: 140.5 | K73: 117.6 | L73: 100.6 | M73: 119.1 | N73: 116.8 | O73: 126.1 | P73: 123.6 | Q73: 123 | R73: 122.6 | S73: 118.6 | T73: 122 | U73: 116.5 | V73: 115.7 | W73: 117.5 | X73: 115.1 | Y73: 110.1 | Z73: 113.9 | AA73: 119.5 | AB73: 109.8 | AC73: 113.8 | AD73: 119.4
A74: Rural | B74: 2015 | C74: January | D74: 123.1 | E74: 123.1 | F74: 122.1 | G74: 124.9 | H74: 111 | I74: 130.4 | J74: 132.3 | K74: 117.2 | L74: 100.5 | M74: 117.2 | N74: 117.9 | O74: 125.6 | P74: 122.8 | Q74: 122.7 | R74: 124.4 | S74: 121.6 | T74: 124 | U74: NA | V74: 118.4 | W74: 118.9 | X74: 116.6 | Y74: 111 | Z74: 114 | AA74: 118.2 | AB74: 110.2 | AC74: 114.5 | AD74: 120.3
A75: Urban | B75: 2015 | C75: January | D75: 124 | E75: 125.5 | F75: 126.6 | G75: 125.2 | H75: 104.3 | I75: 121.3 | J75: 134.4 | K75: 122.9 | L75: 96.1 | M75: 126.6 | N75: 116.5 | O75: 128 | P75: 123.5 | Q75: 127.4 | R75: 121 | S75: 116.1 | T75: 120.2 | U75: 117.3 | V75: 113.4 | W75: 117.2 | X75: 113.7 | Y75: 107.9 | Z75: 114.6 | AA75: 120.8 | AB75: 111.4 | AC75: 113.4 | AD75: 118.5
A76: Rural+Urban | B76: 2015 | C76: January | D76: 123.4 | E76: 123.9 | F76: 123.8 | G76: 125 | H76: 108.5 | I76: 126.2 | J76: 133 | K76: 119.1 | L76: 99 | M76: 120.3 | N76: 117.3 | O76: 126.7 | P76: 123.1 | Q76: 124 | R76: 123.1 | S76: 119.3 | T76: 122.5 | U76: 117.3 | V76: 116.5 | W76: 118.1 | X76: 115.5 | Y76: 109.4 | Z76: 114.3 | AA76: 119.7 | AB76: 110.7 | AC76: 114 | AD76: 119.5
A77: Rural | B77: 2015 | C77: February | D77: 123.4 | E77: 124.4 | F77: 122.1 | G77: 125.8 | H77: 111.5 | I77: 129.4 | J77: 128.2 | K77: 118.8 | L77: 100 | M77: 118.6 | N77: 118.8 | O77: 126.8 | P77: 122.8 | Q77: 124.2 | R77: 125.4 | S77: 122.7 | T77: 125 | U77: NA | V77: 120 | W77: 119.6 | X77: 117.7 | Y77: 110.9 | Z77: 114.8 | AA77: 118.7 | AB77: 110.8 | AC77: 115 | AD77: 120.6
A78: Urban | B78: 2015 | C78: February | D78: 124.3 | E78: 126.5 | F78: 119.5 | G78: 125.6 | H78: 104.9 | I78: 121.6 | J78: 131.8 | K78: 125.1 | L78: 95 | M78: 127.7 | N78: 116.8 | O78: 128.6 | P78: 123.7 | Q78: 128.1 | R78: 121.3 | S78: 116.5 | T78: 120.6 | U78: 118.1 | V78: 114 | W78: 117.7 | X78: 114.1 | Y78: 106.8 | Z78: 114.9 | AA78: 120.4 | AB78: 111.7 | AC78: 113.2 | AD78: 118.7
A79: Rural+Urban | B79: 2015 | C79: February | D79: 123.7 | E79: 125.1 | F79: 121.1 | G79: 125.7 | H79: 109.1 | I79: 125.8 | J79: 129.4 | K79: 120.9 | L79: 98.3 | M79: 121.6 | N79: 118 | O79: 127.6 | P79: 123.1 | Q79: 125.2 | R79: 123.8 | S79: 120.1 | T79: 123.3 | U79: 118.1 | V79: 117.7 | W79: 118.7 | X79: 116.3 | Y79: 108.7 | Z79: 114.9 | AA79: 119.7 | AB79: 111.2 | AC79: 114.1 | AD79: 119.7
A80: Rural | B80: 2015 | C80: March | D80: 123.3 | E80: 124.7 | F80: 118.9 | G80: 126 | H80: 111.8 | I80: 130.9 | J80: 128 | K80: 119.9 | L80: 98.9 | M80: 119.4 | N80: 118.9 | O80: 127.7 | P80: 123.1 | Q80: 124.7 | R80: 126 | S80: 122.9 | T80: 125.5 | U80: NA | V80: 120.6 | W80: 120.2 | X80: 118.2 | Y80: 111.6 | Z80: 115.5 | AA80: 119.4 | AB80: 110.8 | AC80: 115.5 | AD80: 121.1
A81: Urban | B81: 2015 | C81: March | D81: 124 | E81: 126.7 | F81: 113.5 | G81: 125.9 | H81: 104.8 | I81: 123.8 | J81: 131.4 | K81: 127.2 | L81: 93.2 | M81: 127.4 | N81: 117 | O81: 129.2 | P81: 123.9 | Q81: 128.8 | R81: 121.7 | S81: 116.9 | T81: 120.9 | U81: 118.6 | V81: 114.4 | W81: 118 | X81: 114.3 | Y81: 108.4 | Z81: 115.4 | AA81: 120.6 | AB81: 111.3 | AC81: 113.8 | AD81: 119.1
A82: Rural+Urban | B82: 2015 | C82: March | D82: 123.5 | E82: 125.4 | F82: 116.8 | G82: 126 | H82: 109.2 | I82: 127.6 | J82: 129.2 | K82: 122.4 | L82: 97 | M82: 122.1 | N82: 118.1 | O82: 128.4 | P82: 123.4 | Q82: 125.8 | R82: 124.3 | S82: 120.4 | T82: 123.7 | U82: 118.6 | V82: 118.3 | W82: 119.2 | X82: 116.7 | Y82: 109.9 | Z82: 115.4 | AA82: 120.1 | AB82: 111 | AC82: 114.7 | AD82: 120.2
A83: Rural | B83: 2015 | C83: April | D83: 123.3 | E83: 125.5 | F83: 117.2 | G83: 126.8 | H83: 111.9 | I83: 134.2 | J83: 127.5 | K83: 121.5 | L83: 97.8 | M83: 119.8 | N83: 119.4 | O83: 128.7 | P83: 123.6 | Q83: 125.7 | R83: 126.4 | S83: 123.3 | T83: 126 | U83: NA | V83: 121.2 | W83: 120.9 | X83: 118.6 | Y83: 111.9 | Z83: 116.2 | AA83: 119.9 | AB83: 111.6 | AC83: 116 | AD83: 121.5
A84: Urban | B84: 2015 | C84: April | D84: 123.8 | E84: 128.2 | F84: 110 | G84: 126.3 | H84: 104.5 | I84: 130.6 | J84: 130.8 | K84: 131.3 | L84: 91.6 | M84: 127.7 | N84: 117.2 | O84: 129.5 | P84: 124.6 | Q84: 130.1 | R84: 122.1 | S84: 117.2 | T84: 121.3 | U84: 119.2 | V84: 114.7 | W84: 118.4 | X84: 114.6 | Y84: 108.4 | Z84: 115.6 | AA84: 121.7 | AB84: 111.8 | AC84: 114.2 | AD84: 119.7
A85: Rural+Urban | B85: 2015 | C85: April | D85: 123.5 | E85: 126.4 | F85: 114.4 | G85: 126.6 | H85: 109.2 | I85: 132.5 | J85: 128.6 | K85: 124.8 | L85: 95.7 | M85: 122.4 | N85: 118.5 | O85: 129.1 | P85: 124 | Q85: 126.9 | R85: 124.7 | S85: 120.8 | T85: 124.1 | U85: 119.2 | V85: 118.7 | W85: 119.7 | X85: 117.1 | Y85: 110.1 | Z85: 115.9 | AA85: 121 | AB85: 111.7 | AC85: 115.1 | AD85: 120.7
A86: Rural | B86: 2015 | C86: May | D86: 123.5 | E86: 127.1 | F86: 117.3 | G86: 127.7 | H86: 112.5 | I86: 134.1 | J86: 128.5 | K86: 124.3 | L86: 97.6 | M86: 120.7 | N86: 120.2 | O86: 129.8 | P86: 124.4 | Q86: 126.7 | R86: 127.3 | S86: 124.1 | T86: 126.8 | U86: NA | V86: 121.9 | W86: 121.5 | X86: 119.4 | Y86: 113.3 | Z86: 116.7 | AA86: 120.5 | AB86: 112.3 | AC86: 116.9 | AD86: 122.4
A87: Urban | B87: 2015 | C87: May | D87: 123.8 | E87: 129.7 | F87: 111.3 | G87: 126.6 | H87: 105.2 | I87: 130.8 | J87: 135.6 | K87: 142.6 | L87: 90.8 | M87: 128.8 | N87: 117.7 | O87: 129.9 | P87: 126.1 | Q87: 131.3 | R87: 122.4 | S87: 117.4 | T87: 121.6 | U87: 119.6 | V87: 114.9 | W87: 118.7 | X87: 114.9 | Y87: 110.8 | Z87: 116 | AA87: 122 | AB87: 112.4 | AC87: 115.2 | AD87: 120.7
A88: Rural+Urban | B88: 2015 | C88: May | D88: 123.6 | E88: 128 | F88: 115 | G88: 127.3 | H88: 109.8 | I88: 132.6 | J88: 130.9 | K88: 130.5 | L88: 95.3 | M88: 123.4 | N88: 119.2 | O88: 129.8 | P88: 125 | Q88: 127.9 | R88: 125.4 | S88: 121.3 | T88: 124.7 | U88: 119.6 | V88: 119.2 | W88: 120.2 | X88: 117.7 | Y88: 112 | Z88: 116.3 | AA88: 121.4 | AB88: 112.3 | AC88: 116.1 | AD88: 121.6
A89: Rural | B89: 2015 | C89: June | D89: 124.1 | E89: 130.4 | F89: 122.1 | G89: 128.7 | H89: 114.1 | I89: 133.2 | J89: 135.2 | K89: 131.9 | L89: 96.3 | M89: 123 | N89: 121.1 | O89: 131.2 | P89: 126.6 | Q89: 128.2 | R89: 128.4 | S89: 125.1 | T89: 128 | U89: NA | V89: 122.6 | W89: 122.8 | X89: 120.4 | Y89: 114.2 | Z89: 117.9 | AA89: 122 | AB89: 113 | AC89: 117.9 | AD89: 124.1
A90: Urban | B90: 2015 | C90: June | D90: 123.6 | E90: 134.4 | F90: 120.9 | G90: 127.3 | H90: 106 | I90: 132.3 | J90: 146.7 | K90: 148.1 | L90: 89.8 | M90: 130.5 | N90: 118 | O90: 130.5 | P90: 128.5 | Q90: 132.1 | R90: 123.2 | S90: 117.6 | T90: 122.3 | U90: 119 | V90: 115.1 | W90: 119.2 | X90: 115.4 | Y90: 111.7 | Z90: 116.2 | AA90: 123.8 | AB90: 112.5 | AC90: 116 | AD90: 121.7
A91: Rural+Urban | B91: 2015 | C91: June | D91: 123.9 | E91: 131.8 | F91: 121.6 | G91: 128.2 | H91: 111.1 | I91: 132.8 | J91: 139.1 | K91: 137.4 | L91: 94.1 | M91: 125.5 | N91: 119.8 | O91: 130.9 | P91: 127.3 | Q91: 129.2 | R91: 126.4 | S91: 122 | T91: 125.7 | U91: 119 | V91: 119.8 | W91: 121.1 | X91: 118.5 | Y91: 112.9 | Z91: 116.9 | AA91: 123.1 | AB91: 112.8 | AC91: 117 | AD91: 123
A92: Rural | B92: 2015 | C92: July | D92: 124 | E92: 131.5 | F92: 122 | G92: 128.7 | H92: 113.5 | I92: 133.3 | J92: 140.8 | K92: 133.8 | L92: 94.1 | M92: 123.4 | N92: 121 | O92: 131.7 | P92: 127.5 | Q92: 129.4 | R92: 128.8 | S92: 125.5 | T92: 128.3 | U92: NA | V92: 123 | W92: 123 | X92: 120.8 | Y92: 114.1 | Z92: 118 | AA92: 122.9 | AB92: 112.7 | AC92: 118.1 | AD92: 124.7
A93: Urban | B93: 2015 | C93: July | D93: 123.2 | E93: 134.3 | F93: 119.5 | G93: 127.7 | H93: 106.3 | I93: 132.8 | J93: 153.5 | K93: 149.5 | L93: 85.7 | M93: 131.5 | N93: 118.3 | O93: 131.1 | P93: 129.5 | Q93: 133.1 | R93: 123.5 | S93: 117.9 | T93: 122.7 | U93: 119.9 | V93: 115.3 | W93: 119.5 | X93: 116 | Y93: 111.5 | Z93: 116.6 | AA93: 125.4 | AB93: 111.7 | AC93: 116.3 | AD93: 122.4
A94: Rural+Urban | B94: 2015 | C94: July | D94: 123.7 | E94: 132.5 | F94: 121 | G94: 128.3 | H94: 110.9 | I94: 133.1 | J94: 145.1 | K94: 139.1 | L94: 91.3 | M94: 126.1 | N94: 119.9 | O94: 131.4 | P94: 128.2 | Q94: 130.4 | R94: 126.7 | S94: 122.3 | T94: 126.1 | U94: 119.9 | V94: 120.1 | W94: 121.3 | X94: 119 | Y94: 112.7 | Z94: 117.2 | AA94: 124.4 | AB94: 112.3 | AC94: 117.2 | AD94: 123.6
A95: Rural | B95: 2015 | C95: August | D95: 124.7 | E95: 131.3 | F95: 121.3 | G95: 128.8 | H95: 114 | I95: 134.2 | J95: 153.6 | K95: 137.9 | L95: 93.1 | M95: 123.9 | N95: 121.5 | O95: 132.5 | P95: 129.8 | Q95: 130.1 | R95: 129.5 | S95: 126.3 | T95: 129 | U95: NA | V95: 123.8 | W95: 123.7 | X95: 121.1 | Y95: 113.6 | Z95: 118.5 | AA95: 123.6 | AB95: 112.5 | AC95: 118.2 | AD95: 126.1
A96: Urban | B96: 2015 | C96: August | D96: 123.1 | E96: 131.7 | F96: 118.1 | G96: 128 | H96: 106.8 | I96: 130.1 | J96: 165.5 | K96: 156 | L96: 85.3 | M96: 132.7 | N96: 118.8 | O96: 131.7 | P96: 131.1 | Q96: 134.2 | R96: 123.7 | S96: 118.2 | T96: 122.9 | U96: 120.9 | V96: 115.3 | W96: 120 | X96: 116.6 | Y96: 109.9 | Z96: 117.2 | AA96: 126.2 | AB96: 112 | AC96: 116.2 | AD96: 123.2
A97: Rural+Urban | B97: 2015 | C97: August | D97: 124.2 | E97: 131.4 | F97: 120.1 | G97: 128.5 | H97: 111.4 | I97: 132.3 | J97: 157.6 | K97: 144 | L97: 90.5 | M97: 126.8 | N97: 120.4 | O97: 132.1 | P97: 130.3 | Q97: 131.2 | R97: 127.2 | S97: 122.9 | T97: 126.6 | U97: 120.9 | V97: 120.6 | W97: 122 | X97: 119.4 | Y97: 111.7 | Z97: 117.8 | AA97: 125.1 | AB97: 112.3 | AC97: 117.2 | AD97: 124.8
A98: Rural | B98: 2015 | C98: September | D98: 125.1 | E98: 131.1 | F98: 120.7 | G98: 129.2 | H98: 114.7 | I98: 132.3 | J98: 158.9 | K98: 142.1 | L98: 92.5 | M98: 125.4 | N98: 121.9 | O98: 132.7 | P98: 131 | Q98: 131 | R98: 130.4 | S98: 126.8 | T98: 129.9 | U98: NA | V98: 123.7 | W98: 124.5 | X98: 121.4 | Y98: 113.8 | Z98: 119.6 | AA98: 124.5 | AB98: 113.7 | AC98: 118.8 | AD98: 127
A99: Urban | B99: 2015 | C99: September | D99: 123.4 | E99: 129 | F99: 115.6 | G99: 128.3 | H99: 107 | I99: 124 | J99: 168.5 | K99: 165.4 | L99: 86.3 | M99: 134.4 | N99: 119.1 | O99: 132.3 | P99: 131.5 | Q99: 134.7 | R99: 124 | S99: 118.6 | T99: 123.2 | U99: 121.6 | V99: 115.1 | W99: 120.4 | X99: 117.1 | Y99: 109.1 | Z99: 117.3 | AA99: 126.5 | AB99: 112.9 | AC99: 116.2 | AD99: 123.5
A100: Rural+Urban | B100: 2015 | C100: September | D100: 124.6 | E100: 130.4 | F100: 118.7 | G100: 128.9 | H100: 111.9 | I100: 128.4 | J100: 162.2 | K100: 150 | L100: 90.4 | M100: 128.4 | N100: 120.7 | O100: 132.5 | P100: 131.2 | Q100: 132 | R100: 127.9 | S100: 123.4 | T100: 127.2 | U100: 121.6 | V100: 120.4 | W100: 122.6 | X100: 119.8 | Y100: 111.3 | Z100: 118.3 | AA100: 125.7 | AB100: 113.4 | AC100: 117.5 | AD100: 125.4
...

Sheet Cleaned_Data
A1: Sector | B1: Year | C1: Month | D1: Cereals and products | E1: Meat and fish | F1: Egg | G1: Milk and products | H1: Oils and fats | I1: Fruits | J1: Vegetables | K1: Pulses and products | L1: Sugar and Confectionery | M1: Spices | N1: Non-alcoholic beverages | O1: Prepared meals, snacks, sweets etc. | P1: Food and beverages | Q1: Pan, tobacco and intoxicants | R1: Clothing | S1: Footwear | T1: Clothing and footwear | U1: Housing | V1: Fuel and light | W1: Household goods and services | X1: Health | Y1: Transport and communication | Z1: Recreation and amusement | AA1: Education | AB1: Personal care and effects | AC1: Miscellaneous | AD1: General index | AE1: Food | AF1: Apparels | AG1: Utilities | AH1: Personal Care | AI1: Amenities | AJ1: Assorted
A2: Rural | B2: 2013 | C2: January | D2: 107.5 | E2: 106.3 | F2: 108.1 | G2: 104.9 | H2: 106.1 | I2: 103.9 | J2: 101.9 | K2: 106.1 | L2: 106.8 | M2: 103.1 | N2: 104.8 | O2: 106.7 | P2: 105.5 | Q2: 105.1 | R2: 106.5 | S2: 105.8 | T2: 106.4 | U2: 100.3 | V2: 105.5 | W2: 104.8 | X2: 104 | Y2: 103.3 | Z2: 103.4 | AA2: 103.8 | AB2: 104.7 | AC2: 104 | AD2: 105.1 | AE2: =P2+O2+N2+M2+L2+K2+J2+I2+H2+G2+F2+E2+D2 -> 1371.7 | AF2: =SUM(R2:T2) -> 318.7 | AG2: =SUM(Y2,AA2,Z2) -> 310.5 | AH2: =SUM(X2,AB2) -> 208.7 | AI2: =SUM(U2,V2,W2) -> 310.6 | AJ2: =SUM(AC2,Q2) -> 209.1
A3: Urban | B3: 2013 | C3: January | D3: 110.5 | E3: 109.1 | F3: 113 | G3: 103.6 | H3: 103.4 | I3: 102.3 | J3: 102.9 | K3: 105.8 | L3: 105.1 | M3: 101.8 | N3: 105.1 | O3: 107.9 | P3: 105.9 | Q3: 105.2 | R3: 105.9 | S3: 105 | T3: 105.8 | U3: 100.3 | V3: 105.4 | W3: 104.8 | X3: 104.1 | Y3: 103.2 | Z3: 102.9 | AA3: 103.5 | AB3: 104.3 | AC3: 103.7 | AD3: 104 | AE3: =P3+O3+N3+M3+L3+K3+J3+I3+H3+G3+F3+E3+D3 -> 1376.4 | AF3: =SUM(R3:T3) -> 316.7 | AG3: =SUM(Y3,AA3,Z3) -> 309.6 | AH3: =SUM(X3,AB3) -> 208.4 | AI3: =SUM(U3,V3,W3) -> 310.5 | AJ3: =SUM(AC3,Q3) -> 208.9
A4: Rural+Urban | B4: 2013 | C4: January | D4: 108.4 | E4: 107.3 | F4: 110 | G4: 104.4 | H4: 105.1 | I4: 103.2 | J4: 102.2 | K4: 106 | L4: 106.2 | M4: 102.7 | N4: 104.9 | O4: 107.3 | P4: 105.6 | Q4: 105.1 | R4: 106.3 | S4: 105.5 | T4: 106.2 | U4: 100.3 | V4: 105.5 | W4: 104.8 | X4: 104 | Y4: 103.2 | Z4: 103.1 | AA4: 103.6 | AB4: 104.5 | AC4: 103.9 | AD4: 104.6 | AE4: =P4+O4+N4+M4+L4+K4+J4+I4+H4+G4+F4+E4+D4 -> 1373.3 | AF4: =SUM(R4:T4) -> 318 | AG4: =SUM(Y4,AA4,Z4) -> 309.9 | AH4: =SUM(X4,AB4) -> 208.5 | AI4: =SUM(U4,V4,W4) -> 310.6 | AJ4: =SUM(AC4,Q4) -> 209
A5: Rural | B5: 2013 | C5: February | D5: 109.2 | E5: 108.7 | F5: 110.2 | G5: 105.4 | H5: 106.7 | I5: 104 | J5: 102.4 | K5: 105.9 | L5: 105.7 | M5: 103.1 | N5: 105.1 | O5: 107.7 | P5: 106.3 | Q5: 105.6 | R5: 107.1 | S5: 106.3 | T5: 107 | U5: 100.4 | V5: 106.2 | W5: 105.2 | X5: 104.4 | Y5: 103.9 | Z5: 104 | AA5: 104.1 | AB5: 104.6 | AC5: 104.4 | AD5: 105.8 | AE5: =P5+O5+N5+M5+L5+K5+J5+I5+H5+G5+F5+E5+D5 -> 1380.4 | AF5: =SUM(R5:T5) -> 320.4 | AG5: =SUM(Y5,AA5,Z5) -> 312 | AH5: =SUM(X5,AB5) -> 209 | AI5: =SUM(U5,V5,W5) -> 311.8 | AJ5: =SUM(AC5,Q5) -> 210
A6: Urban | B6: 2013 | C6: February | D6: 112.9 | E6: 112.9 | F6: 116.9 | G6: 104 | H6: 103.5 | I6: 103.1 | J6: 104.9 | K6: 104.1 | L6: 103.8 | M6: 102.3 | N6: 106 | O6: 109 | P6: 107.2 | Q6: 106 | R6: 106.6 | S6: 105.5 | T6: 106.4 | U6: 100.4 | V6: 105.7 | W6: 105.2 | X6: 104.7 | Y6: 104.4 | Z6: 103.3 | AA6: 103.7 | AB6: 104.3 | AC6: 104.3 | AD6: 104.7 | AE6: =P6+O6+N6+M6+L6+K6+J6+I6+H6+G6+F6+E6+D6 -> 1390.6 | AF6: =SUM(R6:T6) -> 318.5 | AG6: =SUM(Y6,AA6,Z6) -> 311.4 | AH6: =SUM(X6,AB6) -> 209 | AI6: =SUM(U6,V6,W6) -> 311.3 | AJ6: =SUM(AC6,Q6) -> 210.3
A7: Rural+Urban | B7: 2013 | C7: February | D7: 110.4 | E7: 110.2 | F7: 112.8 | G7: 104.9 | H7: 105.5 | I7: 103.6 | J7: 103.2 | K7: 105.3 | L7: 105.1 | M7: 102.8 | N7: 105.5 | O7: 108.3 | P7: 106.6 | Q7: 105.7 | R7: 106.9 | S7: 106 | T7: 106.8 | U7: 100.4 | V7: 106 | W7: 105.2 | X7: 104.5 | Y7: 104.2 | Z7: 103.6 | AA7: 103.9 | AB7: 104.5 | AC7: 104.4 | AD7: 105.3 | AE7: =P7+O7+N7+M7+L7+K7+J7+I7+H7+G7+F7+E7+D7 -> 1384.2 | AF7: =SUM(R7:T7) -> 319.7 | AG7: =SUM(Y7,AA7,Z7) -> 311.7 | AH7: =SUM(X7,AB7) -> 209 | AI7: =SUM(U7,V7,W7) -> 311.6 | AJ7: =SUM(AC7,Q7) -> 210.1
A8: Rural | B8: 2013 | C8: March | D8: 110.2 | E8: 108.8 | F8: 109.9 | G8: 105.6 | H8: 106.2 | I8: 105.7 | J8: 101.4 | K8: 105.7 | L8: 105 | M8: 103.3 | N8: 105.6 | O8: 108.2 | P8: 106.6 | Q8: 106.5 | R8: 107.6 | S8: 106.8 | T8: 107.5 | U8: 100.4 | V8: 106.1 | W8: 105.6 | X8: 104.7 | Y8: 104.6 | Z8: 104 | AA8: 104.3 | AB8: 104.3 | AC8: 104.6 | AD8: 106 | AE8: =P8+O8+N8+M8+L8+K8+J8+I8+H8+G8+F8+E8+D8 -> 1382.2 | AF8: =SUM(R8:T8) -> 321.9 | AG8: =SUM(Y8,AA8,Z8) -> 312.9 | AH8: =SUM(X8,AB8) -> 209 | AI8: =SUM(U8,V8,W8) -> 312.1 | AJ8: =SUM(AC8,Q8) -> 211.1
A9: Urban | B9: 2013 | C9: March | D9: 113.9 | E9: 111.4 | F9: 113.2 | G9: 104.3 | H9: 102.7 | I9: 104.9 | J9: 103.8 | K9: 103.5 | L9: 102.6 | M9: 102.4 | N9: 107 | O9: 109.8 | P9: 107.3 | Q9: 106.8 | R9: 107.2 | S9: 106 | T9: 107 | U9: 100.4 | V9: 106 | W9: 105.7 | X9: 105.2 | Y9: 105.5 | Z9: 103.5 | AA9: 103.8 | AB9: 104.2 | AC9: 104.9 | AD9: 105 | AE9: =P9+O9+N9+M9+L9+K9+J9+I9+H9+G9+F9+E9+D9 -> 1386.8 | AF9: =SUM(R9:T9) -> 320.2 | AG9: =SUM(Y9,AA9,Z9) -> 312.8 | AH9: =SUM(X9,AB9) -> 209.4 | AI9: =SUM(U9,V9,W9) -> 312.1 | AJ9: =SUM(AC9,Q9) -> 211.7
A10: Rural+Urban | B10: 2013 | C10: March | D10: 111.4 | E10: 109.7 | F10: 111.2 | G10: 105.1 | H10: 104.9 | I10: 105.3 | J10: 102.2 | K10: 105 | L10: 104.2 | M10: 103 | N10: 106.2 | O10: 108.9 | P10: 106.9 | Q10: 106.6 | R10: 107.4 | S10: 106.5 | T10: 107.3 | U10: 100.4 | V10: 106.1 | W10: 105.6 | X10: 104.9 | Y10: 105.1 | Z10: 103.7 | AA10: 104 | AB10: 104.3 | AC10: 104.7 | AD10: 105.5 | AE10: =P10+O10+N10+M10+L10+K10+J10+I10+H10+G10+F10+E10+D10 -> 1384 | AF10: =SUM(R10:T10) -> 321.2 | AG10: =SUM(Y10,AA10,Z10) -> 312.8 | AH10: =SUM(X10,AB10) -> 209.2 | AI10: =SUM(U10,V10,W10) -> 312.1 | AJ10: =SUM(AC10,Q10) -> 211.3
A11: Rural | B11: 2013 | C11: April | D11: 110.2 | E11: 109.5 | F11: 106.9 | G11: 106.3 | H11: 105.7 | I11: 108.3 | J11: 103.4 | K11: 105.7 | L11: 104.2 | M11: 103.2 | N11: 106.5 | O11: 108.8 | P11: 107.1 | Q11: 107.1 | R11: 108.1 | S11: 107.4 | T11: 108 | U11: 100.5 | V11: 106.5 | W11: 106.1 | X11: 105.1 | Y11: 104.4 | Z11: 104.5 | AA11: 104.8 | AB11: 102.7 | AC11: 104.6 | AD11: 106.4 | AE11: =P11+O11+N11+M11+L11+K11+J11+I11+H11+G11+F11+E11+D11 -> 1385.8 | AF11: =SUM(R11:T11) -> 323.5 | AG11: =SUM(Y11,AA11,Z11) -> 313.7 | AH11: =SUM(X11,AB11) -> 207.8 | AI11: =SUM(U11,V11,W11) -> 313.1 | AJ11: =SUM(AC11,Q11) -> 211.7
A12: Urban | B12: 2013 | C12: April | D12: 114.6 | E12: 113.4 | F12: 106 | G12: 104.7 | H12: 102.1 | I12: 109.5 | J12: 109.7 | K12: 104.6 | L12: 102 | M12: 103.5 | N12: 108.2 | O12: 110.6 | P12: 108.8 | Q12: 108.5 | R12: 107.9 | S12: 106.4 | T12: 107.7 | U12: 100.5 | V12: 106.4 | W12: 106.5 | X12: 105.7 | Y12: 105 | Z12: 104 | AA12: 105.2 | AB12: 103.2 | AC12: 105.1 | AD12: 105.7 | AE12: =P12+O12+N12+M12+L12+K12+J12+I12+H12+G12+F12+E12+D12 -> 1397.7 | AF12: =SUM(R12:T12) -> 322 | AG12: =SUM(Y12,AA12,Z12) -> 314.2 | AH12: =SUM(X12,AB12) -> 208.9 | AI12: =SUM(U12,V12,W12) -> 313.4 | AJ12: =SUM(AC12,Q12) -> 213.6
A13: Rural+Urban | B13: 2013 | C13: April | D13: 111.6 | E13: 110.9 | F13: 106.6 | G13: 105.7 | H13: 104.4 | I13: 108.9 | J13: 105.5 | K13: 105.3 | L13: 103.5 | M13: 103.3 | N13: 107.2 | O13: 109.6 | P13: 107.7 | Q13: 107.5 | R13: 108 | S13: 107 | T13: 107.9 | U13: 100.5 | V13: 106.5 | W13: 106.3 | X13: 105.3 | Y13: 104.7 | Z13: 104.2 | AA13: 105 | AB13: 102.9 | AC13: 104.8 | AD13: 106.1 | AE13: =P13+O13+N13+M13+L13+K13+J13+I13+H13+G13+F13+E13+D13 -> 1390.2 | AF13: =SUM(R13:T13) -> 322.9 | AG13: =SUM(Y13,AA13,Z13) -> 313.9 | AH13: =SUM(X13,AB13) -> 208.2 | AI13: =SUM(U13,V13,W13) -> 313.3 | AJ13: =SUM(AC13,Q13) -> 212.3
... A373: Rural+Urban | B373: 2023 | C373: May | D373: 173.7 | E373: 214.3 | F373: 173.2 | G373: 179.5 | H373: 170 | I373: 172.2 | J373: 161 | K373: 175.6 | L373: 122.7 | M373: 218 | N373: 173.4 | O373: 194.2 | P373: 179.1 | Q373: 201 | R373: 187.3 | S373: 179.7 | T373: 186.2 | U373: 175.6 | V373: 182.8 | W373: 175.2 | X373: 185.7 | Y373: 164.8 | Z373: 171.2 | AA373: 177.1 | AB373: 185.2 | AC373: 175.7 | AD373: 179.1 | AE373: =P373+O373+N373+M373+L373+K373+J373+I373+H373+G373+F373+E373+D373 -> 2306.9 | AF373: =SUM(R373:T373) -> 553.2 | AG373: =SUM(Y373,AA373,Z373) -> 513.1 | AH373: =SUM(X373,AB373) -> 370.9 | AI373: =SUM(U373,V373,W373) -> 533.6 | AJ373: =SUM(AC373,Q373) -> 376.7

Sheet PS_1
A1: Latest Month Data
A3: Year_2023 | C3: Month_May | E3: Percentage in Respect to Total
A4: Sector | B4: Rural | C4: Urban | D4: Rural+Urban | E4: Rural | F4: Urban | G4: Rural+Urban
A5: Cereals and products | B5: 173.2 | C5: 174.7 | D5: 173.7 | E5: =(B5/$B$32)*100 -> 3.5680442 | F5: =(C5/$C$32)*100 -> 3.6251582 | G5: =(D5/$D$32)*100 -> 3.5936692
A6: Meat and fish | B6: 211.5 | C6: 219.4 | D6: 214.3 | E6: =(B6/$B$32)*100 -> 4.3570516 | F6: =(C6/$C$32)*100 -> 4.5527173 | G6: =(D6/$D$32)*100 -> 4.4336402
A7: Egg | B7: 171 | C7: 176.7 | D7: 173.2 | E7: =(B7/$B$32)*100 -> 3.5227226 | F7: =(C7/$C$32)*100 -> 3.6666597 | G7: =(D7/$D$32)*100 -> 3.5833247
A8: Milk and products | B8: 179.6 | C8: 179.4 | D8: 179.5 | E8: =(B8/$B$32)*100 -> 3.6998888 | F8: =(C8/$C$32)*100 -> 3.7226868 | G8: =(D8/$D$32)*100 -> 3.713665
A9: Oils and fats | B9: 173.3 | C9: 164.4 | D9: 170 | E9: =(B9/$B$32)*100 -> 3.5701042 | F9: =(C9/$C$32)*100 -> 3.4114254 | G9: =(D9/$D$32)*100 -> 3.5171201
A10: Fruits | B10: 169 | C10: 175.8 | D10: 172.2 | E10: =(B10/$B$32)*100 -> 3.4815212 | F10: =(C10/$C$32)*100 -> 3.6479841 | G10: =(D10/$D$32)*100 -> 3.5626358
A11: Vegetables | B11: 148.7 | C11: 185 | D11: 161 | E11: =(B11/$B$32)*100 -> 3.0633266 | F11: =(C11/$C$32)*100 -> 3.8388911 | G11: =(D11/$D$32)*100 -> 3.3309196
A12: Pulses and products | B12: 174.9 | C12: 176.9 | D12: 175.6 | E12: =(B12/$B$32)*100 -> 3.6030654 | F12: =(C12/$C$32)*100 -> 3.6708099 | G12: =(D12/$D$32)*100 -> 3.6329782
A13: Sugar and Confectionery | B13: 121.9 | C13: 124.2 | D13: 122.7 | E13: =(B13/$B$32)*100 -> 2.5112274 | F13: =(C13/$C$32)*100 -> 2.5772447 | G13: =(D13/$D$32)*100 -> 2.5385332
A14: Spices | B14: 221 | C14: 211.9 | D14: 218 | E14: =(B14/$B$32)*100 -> 4.5527584 | F14: =(C14/$C$32)*100 -> 4.3970866 | G14: =(D14/$D$32)*100 -> 4.5101893
A15: Non-alcoholic beverages | B15: 178.7 | C15: 165.9 | D15: 173.4 | E15: =(B15/$B$32)*100 -> 3.6813481 | F15: =(C15/$C$32)*100 -> 3.4425515 | G15: =(D15/$D$32)*100 -> 3.5874625
A16: Prepared meals, snacks, sweets etc. | B16: 191.1 | C16: 197.7 | D16: 194.2 | E16: =(B16/$B$32)*100 -> 3.936797 | F16: =(C16/$C$32)*100 -> 4.1024258 | G16: =(D16/$D$32)*100 -> 4.0177925
... A31: General index | B31: 179.8 | C31: 178.2 | D31: 179.1 | E31: =(B31/$B$32)*100 -> 3.7040089 | F31: =(C31/$C$32)*100 -> 3.6977859 | G31: =(D31/$D$32)*100 -> 3.7053895
A32: Total | B32: =SUM(B5:B31) -> 4854.2 | C32: =SUM(C5:C31) -> 4819.1 | D32: =SUM(D5:D31) -> 4833.5 | E32: 100 | F32: 100 | G32: 100
A33: Eatables | B33: 2290.7 | C33: 2335.1 | D33: 2306.9 | E33: =(B33/$B$32*100) -> 47.190062 | F33: =(C33/$C$32*100) -> 48.455106 | G33: =(D33/$D$32*100) -> 47.72732
A34: Apparels | B34: 569.9 | C34: 528.7 | D34: 553.2 | E34: =(B34/$B$32*100) -> 11.740349 | F34: =(C34/$C$32*100) -> 10.970928 | G34: =(D34/$D$32*100) -> 11.445123
A35: Utilities | B35: 523.8 | C35: 504.4 | D35: 513.1 | E35: =(B35/$B$32*100) -> 10.790656 | F35: =(C35/$C$32*100) -> 10.466685 | G35: =(D35/$D$32*100) -> 10.615496
A36: Personal Care | B36: 372.7 | C36: 367.8 | D36: 370.9 | E36: =(B36/$B$32*100) -> 7.6778872 | F36: =(C36/$C$32*100) -> 7.6321305 | G36: =(D36/$D$32*100) -> 7.6735285
A37: Amenities | B37: 537.9 | C37: 529.1 | D37: 533.6 | E37: =(B37/$B$32*100) -> 11.081126 | F37: =(C37/$C$32*100) -> 10.979228 | G37: =(D37/$D$32*100) -> 11.039619
A38: Assorted | B38: 379.4 | C38: 375.8 | D38: 376.7 | E38: =(B38/$B$32*100) -> 7.815912 | F38: =(C38/$C$32*100) -> 7.7981366 | G38: =(D38/$D$32*100) -> 7.7935244
A41: Interpretation
A42: 1:- The CPI inflation based on latest months (Jan 23 to may 23) data in all the sectors of Eatables category is close to 48%.
A43: 2:- This indicates a sharp rise in price over the first quarter especially in Eatables category.
A44: 3:- The increased inflation rate may be due to weather, supply chain, fuel price hike, input cost, demand and taxation.
A45: 4:- The food inflation affects everyone but mostly affect poor and low income household, middle class, food business.
A46: 5:-It increases poverty and reduce nutrition, the government needs to act on it efficiently.
A47: 6:-The government may take action in order to reduce import duties to lower the cost price and increase the number of cold storage houses to preserve the food effectively.

Sheet PS_2
A1: Y-O-Y CPI Growth from 2017
A3: Sum of General index | B3: Year
A4: Month | B4: 2017 | C4: 2018 | D4: 2019 | E4: 2020 | F4: 2021 | G4: 2022 | H4: 2023 | I4: Grand Total
A5: January | B5: 390.5 | C5: 410.3 | D5: 418.6 | E5: 450.3 | F5: 471.8 | G5: 497.1 | H5: 529.2 | I5: 3167.8
A6: December | B6: 411.1 | C6: 420 | D6: 451 | E6: 476.5 | F6: 498.4 | G6: 526.9 | I6: 2783.9
A7: Grand Total | B7: 801.6 | C7: 830.3 | D7: 869.6 | E7: 926.8 | F7: 970.2 | G7: 1024 | H7: 529.2 | I7: 5951.7
A9: Row labels | B9: 2017 | C9: 2018 | D9: 2019 | E9: 2020 | F9: 2021 | G9: 2022 | H9: 2023 | K9: Row labels | L9: Y-o-Y Inflation
A10: January | B10: =B5 -> 390.5 | C10: =C5 -> 410.3 | D10: =D5 -> 418.6 | E10: =E5 -> 450.3 | F10: =F5 -> 471.8 | G10: =G5 -> 497.1 | H10: =H5 -> 529.2 | K10: 2017 | L10: 5.0109462
A11: December | B11: =B6 -> 411.1 | C11: =C6 -> 420 | D11: =D6 -> 451 | E11: =E6 -> 476.5 | F11: =F6 -> 498.4 | G11: =G6 -> 526.9 | H11: 553.2 | K11: 2018 | L11: 2.3095238
A12: Y-o-Y Inflation | B12: =((B11-B10)/B11)*100 -> 5.0109462 | C12: =((C11-C10)/C11)*100 -> 2.3095238 | D12: =((D11-D10)/D11)*100 -> 7.1840355 | E12: =((E11-E10)/E11)*100 -> 5.498426 | F12: =((F11-F10)/F11)*100 -> 5.3370787 | G12: =((G11-G10)/G11)*100 -> 5.6557221 | H12: =((H11-H10)/H11)*100 -> 4.3383948 | K12: 2019 | L12: 7.1840355
K13: 2020 | L13: 5.498426
K14: 2021 | L14: 5.3370787
K15: 2022 | L15: 5.6557221
K16: 2023 | L16: 4.3383948
N27: INTERPRETATION
N28: Year from 2019-2022 Shows the Heighest Inflation
N29: The spike aligns with:COVID-19 supply chain disruptions,Fuel price increases

Sheet PS_3
A1: Analysis for 12 Months ending on May 2023(Sector- Rural+Urban)
A3: Year | B3: 2022 | C3: 2022 | D3: 2022 | E3: 2022 | F3: 2022 | G3: 2022 | H3: 2022 | I3: 2022 | J3: 2023 | K3: 2023 | L3: 2023 | M3: 2023 | N3: 2023
A4: Month | B4: May | C4: June | D4: July | E4: August | F4: September | G4: October | H4: November | I4: December | J4: January | K4: February | L4: March | M4: April | N4: May | O4: Year on Year Inflation
A5: Cereals and products | B5: 154.1 | C5: 155 | D5: 156.5 | E5: 160.3 | F5: 163.5 | G5: 165.2 | H5: 167.4 | I5: 169.2 | J5: 173.8 | K5: 174.4 | L5: 174.4 | M5: 173.8 | N5: 173.7 | O5: =(N5-PS_3!B5)/PS_3!B5*100 -> 12.719014
A6: Meat and fish | B6: 217 | C6: 219.4 | D6: 213 | E6: 206.5 | F6: 209.2 | G6: 210.9 | H6: 209.4 | I6: 209 | J6: 210.7 | K6: 207.7 | L6: 207.7 | M6: 209.3 | N6: 214.3 | O6: =(N6-PS_3!B6)/PS_3!B6*100 -> -1.2442396
A7: Egg | B7: 162.4 | C7: 170.8 | D7: 175.2 | E7: 169.2 | F7: 169.7 | G7: 170.9 | H7: 181.4 | I7: 190.2 | J7: 194.5 | K7: 175.2 | L7: 175.2 | M7: 169.6 | N7: 173.2 | O7: =(N7-PS_3!B7)/PS_3!B7*100 -> 6.6502463
A8: Milk and products | B8: 164.9 | C8: 165.8 | D8: 166.6 | E8: 168.1 | F8: 169.7 | G8: 170.9 | H8: 172.3 | I8: 173.6 | J8: 174.6 | K8: 177.3 | L8: 177.3 | M8: 178.4 | N8: 179.5 | O8: =(N8-PS_3!B8)/PS_3!B8*100 -> 8.8538508
A9: Oils and fats | B9: 202.4 | C9: 200.9 | D9: 195.8 | E9: 192.4 | F9: 188.7 | G9: 186.5 | H9: 188.9 | I9: 188.5 | J9: 187.2 | K9: 179.3 | L9: 179.2 | M9: 174.9 | N9: 170 | O9: =(N9-PS_3!B9)/PS_3!B9*100 -> -16.007905
A10: Fruits | B10: 171 | C10: 169.7 | D10: 174.2 | E10: 172.9 | F10: 165.7 | G10: 163.8 | H10: 160.7 | I10: 158 | J10: 158.3 | K10: 169.5 | L10: 169.5 | M10: 176.3 | N10: 172.2 | O10: =(N10-PS_3!B10)/PS_3!B10*100 -> 0.70175439
A11: Vegetables | B11: 174.9 | C11: 182.3 | D11: 182.1 | E11: 186.7 | F11: 191.8 | G11: 199.7 | H11: 183.1 | I11: 159.9 | J11: 153.9 | K11: 152.7 | L11: 152.8 | M11: 155.4 | N11: 161 | O11: =(N11-PS_3!B11)/PS_3!B11*100 -> -7.9473985
A12: Pulses and products | B12: 164.7 | C12: 164.3 | D12: 164.3 | E12: 167.2 | F12: 169.1 | G12: 169.8 | H12: 170.5 | I12: 170.8 | J12: 170.9 | K12: 171 | L12: 171.1 | M12: 173.4 | N12: 175.6 | O12: =(N12-PS_3!B12)/PS_3!B12*100 -> 6.6180935
A13: Sugar and Confectionery | B13: 119.7 | C13: 119.9 | D13: 120 | E13: 120.9 | F13: 121.6 | G13: 121.9 | H13: 122.1 | I13: 121.8 | J13: 121.1 | K13: 120 | L13: 120 | M13: 121.3 | N13: 122.7 | O13: =(N13-PS_3!B13)/PS_3!B13*100 -> 2.5062657
A14: Spices | B14: 184.9 | C14: 187.1 | D14: 190 | E14: 193.6 | F14: 197.3 | G14: 199.9 | H14: 202.8 | I14: 205.2 | J14: 208.4 | K14: 209.7 | L14: 209.7 | M14: 212.9 | N14: 218 | O14: =(N14-PS_3!B14)/PS_3!B14*100 -> 17.901568
A15: Non-alcoholic beverages | B15: 167.1 | C15: 167.9 | D15: 168.4 | E15: 168.8 | F15: 169.4 | G15: 169.9 | H15: 170.4 | I15: 171 | J15: 171.4 | K15: 172.3 | L15: 172.3 | M15: 172.9 | N15: 173.4 | O15: =(N15-PS_3!B15)/PS_3!B15*100 -> 3.7701975
A16: Prepared meals, snacks, sweets etc. | B16: 182.5 | C16: 183.9 | D16: 185.2 | E16: 186.3 | F16: 187.4 | G16: 188.3 | H16: 189.5 | I16: 190.3 | J16: 191.2 | K16: 193 | L16: 193 | M16: 193.5 | N16: 194.2 | O16: =(N16-PS_3!B16)/PS_3!B16*100 -> 6.4109589
... A31: General index | B31: 171.7 | C31: 172.6 | D31: 173.4 | E31: 174.3 | F31: 175.3 | G31: 176.7 | H31: 176.5 | I31: 175.7 | J31: 176.5 | K31: 177.2 | L31: 177.2 | M31: 178.1 | N31: 179.1 | O31: =(N31-PS_3!B31)/PS_3!B31*100 -> 4.3098427
A32: Eatables | B32: =B17+B16+B15+B14+B13+B12+B11+B10+B9+B8+B7+B6+B5 -> 2238.9 | C32: =C17+C16+C15+C14+C13+C12+C11+C10+C9+C8+C7+C6+C5 -> 2261.9 | D32: =D17+D16+D15+D14+D13+D12+D11+D10+D9+D8+D7+D6+D5 -> 2266.3 | E32: =E17+E16+E15+E14+E13+E12+E11+E10+E9+E8+E7+E6+E5 -> 2269.2 | F32: =F17+F16+F15+F14+F13+F12+F11+F10+F9+F8+F7+F6+F5 -> 2280.9 | G32: =G17+G16+G15+G14+G13+G12+G11+G10+G9+G8+G7+G6+G5 -> 2297.3 | H32: =H17+H16+H15+H14+H13+H12+H11+H10+H9+H8+H7+H6+H5 -> 2296.8 | I32: =I17+I16+I15+I14+I13+I12+I11+I10+I9+I8+I7+I6+I5 -> 2283.4 | ... N32: =N17+N16+N15+N14+N13+N12+N11+N10+N9+N8+N7+N6+N5 -> 2306.9 | O32: =(N32-PS_3!B32)/PS_3!B32*100 -> 3.0372058
A33: Apparels | B33: =SUM(B19:B21) -> 518.6 | C33: =SUM(C19:C21) -> 523 | D33: =SUM(D19:D21) -> 526.9 | E33: =SUM(E19:E21) -> 530.7 | F33: =SUM(F19:F21) -> 535.1 | G33: =SUM(G19:G21) -> 538.2 | H33: =SUM(H19:H21) -> 541.4 | I33: =SUM(I19:I21) -> 544 | ... N33: =SUM(N19:N21) -> 553.2 | O33: =(N33-PS_3!B33)/PS_3!B33*100 -> 6.6718087
A34: Utilities | B34: =SUM(B26,B28,B27) -> 496 | C34: =SUM(C26,C28,C27) -> 495.9 | D34: =SUM(D26,D28,D27) -> 499.3 | E34: =SUM(E26,E28,E27) -> 501.1 | F34: =SUM(F26,F28,F27) -> 503 | G34: =SUM(G26,G28,G27) -> 504.5 | H34: =SUM(H26,H28,H27) -> 505.2 | I34: =SUM(I26,I28,I27) -> 506.4 | ... N34: =SUM(N26,N28,N27) -> 513.1 | O34: =(N34-PS_3!B34)/PS_3!B34*100 -> 3.4475806
A35: Personal Care | B35: =SUM(B25,B29) -> 343.2 | C35: =SUM(C25,C29) -> 344.8 | D35: =SUM(D25,D29) -> 345.8 | E35: =SUM(E25,E29) -> 348 | F35: =SUM(F25,F29) -> 348.7 | G35: =SUM(G25,G29) -> 350.8 | H35: =SUM(H25,H29) -> 353.4 | I35: =SUM(I25,I29) -> 356.9 | ... N35: =SUM(N25,N29) -> 370.9 | O35: =(N35-PS_3!B35)/PS_3!B35*100 -> 8.0710956
A36: Amenities | B36: =SUM(B22,B23,B24) -> 507.3 | C36: =SUM(C22,C23,C24) -> 509.2 | D36: =SUM(D22,D23,D24) -> 514.8 | E36: =SUM(E22,E23,E24) -> 516.3 | F36: =SUM(F22,F23,F24) -> 518.5 | G36: =SUM(G22,G23,G24) -> 522.1 | H36: =SUM(H22,H23,H24) -> 524.5 | I36: =SUM(I22,I23,I24) -> 524.8 | ... N36: =SUM(N22,N23,N24) -> 533.6 | O36: =(N36-PS_3!B36)/PS_3!B36*100 -> 5.1843091
A37: Assorted | B37: =SUM(B30,B18) -> 361.6 | C37: =SUM(C30,C18) -> 361.8 | D37: =SUM(D30,D18) -> 363 | E37: =SUM(E30,E18) -> 364.1 | F37: =SUM(F30,F18) -> 365.6 | G37: =SUM(G30,G18) -> 366.8 | H37: =SUM(H30,H18) -> 368 | I37: =SUM(I30,I18) -> 369.3 | ... N37: =SUM(N30,N18) -> 376.7 | O37: =(N37-PS_3!B37)/PS_3!B37*100 -> 4.175885
A40: Month on Month Inflation Rate on Eatables Category
A41: Months | B41: Rate of Inflation
A42: June | B42: =(C32-B32)/B32*100 -> 1.0272902 | C42: Highest | N42: Interpretation
A43: July | B43: =(D32-C32)/C32*100 -> 0.19452673 | N43: :- The CPI inflation data in rural+urban sector June-2022 inflation rate is highest (1.03%)
A44: August | B44: =(E32-D32)/D32*100 -> 0.12796188 | N44: and February-2023 inflation rate is lowest (-0.59%) .
A45: September | B45: =(F32-E32)/E32*100 -> 0.51560021
A46: October | B46: =(G32-F32)/F32*100 -> 0.71901442
A47: November | B47: =(H32-G32)/G32*100 -> -0.02176468
A48: December | B48: =(I32-H32)/H32*100 -> -0.58342041
A49: January | B49: =(J32-I32)/I32*100 -> 0.40728738
A50: February | B50: =(K32-J32)/J32*100 -> -0.59318707 | C50: Lowest
A51: March | B51: =(L32-K32)/K32*100 -> 0.0043876969
A52: April | B52: =(M32-L32)/L32*100 -> 0.45630046
A53: May | B53: =(N32-M32)/M32*100 -> 0.7555905
A57: Absolute Changes in Inflation on Eatables Category
A58: Eatables | B58: Rate of Inflation
A59: Cereals and products | B59: 12.719014
A60: Meat and fish | B60: -1.2442396 | N60: Interpretation
A61: Egg | B61: 6.6502463 | N61: :- The CPI inflation (in individual Eatables Category) data in rural+urban sector Spices Category inflation rate is highest (17.90%)
A62: Milk and products | B62: 8.8538508 | N62: and Oil & Fats Category inflation rate is lowest (-16.01%).
A63: Oils and fats | B63: -16.007905 | C63: Lowest | N63: Inflation is volatile indicating seasonal constraints and weather dispensiceries
A64: Fruits | B64: 0.70175439
A65: Vegetables | B65: -7.9473985
A66: Pulses and products | B66: 6.6180935
A67: Sugar and Confectionery | B67: 2.5062657
A68: Spices | B68: 17.901568 | C68: Highest
A69: Non-alcoholic beverages | B69: 3.7701975
A70: Prepared meals, snacks, sweets etc. | B70: 6.4109589
A71: Food and beverages | B71: 3.3467975

Sheet PS_4
A1: Impact of COVID-19 Pandemic on Inflation Rate(Sector- Rural+Urban)
A3: Onset of Pandemic
A5: Year | B5: 2019 | C5: 2019 | D5: 2019 | E5: 2019 | F5: 2019 | G5: 2019 | H5: 2019 | I5: 2019 | J5: 2019 | K5: 2020 | L5: 2020 | M5: 2020 | N5: Inflation Rate%
A6: Month | B6: March | C6: May | D6: June | E6: July | F6: August | G6: September | H6: October | I6: November | J6: December | K6: January | L6: February | M6: March
A7: Cereals and products | B7: 137.8 | C7: 138.3 | D7: 138.7 | E7: 139.3 | F7: 140.1 | G7: 140.9 | H7: 141.8 | I7: 142.5 | J7: 143.5 | K7: 144.3 | L7: 144.8 | M7: 145.1 | N7: =(M7-B7)/B7*100 -> 5.2975327
A8: Meat and fish | B8: 153 | C8: 158.5 | D8: 162.1 | E8: 162.7 | F8: 160.6 | G8: 160.8 | H8: 161 | I8: 163.2 | J8: 165 | K8: 167.4 | L8: 167.5 | M8: 167 | N8: =(M8-B8)/B8*100 -> 9.1503268
A9: Egg | B9: 140.3 | C9: 136 | D9: 137.8 | E9: 140 | F9: 138.5 | G9: 139.6 | H9: 142.6 | I9: 145.6 | J9: 151.1 | K9: 154.9 | L9: 151.8 | M9: 148.1 | N9: =(M9-B9)/B9*100 -> 5.5595153
A10: Milk and products | B10: 142.3 | C10: 142.5 | D10: 143.3 | E10: 144 | F10: 144.7 | G10: 145.4 | H10: 146.2 | I10: 146.7 | J10: 148.3 | K10: 150.1 | L10: 150.8 | M10: 151.5 | N10: =(M10-B10)/B10*100 -> 6.4652143
A11: Oils and fats | B11: 122 | C11: 122 | D11: 122.2 | E11: 122.5 | F11: 122.9 | G11: 123.5 | H11: 123.9 | I11: 124.3 | J11: 125.7 | K11: 129.9 | L11: 131.4 | M11: 131.2 | N11: =(M11-B11)/B11*100 -> 7.5409836
A12: Fruits | B12: 137.6 | C12: 146.5 | D12: 146.8 | E12: 150.3 | F12: 149.4 | G12: 146.6 | H12: 148 | I12: 147.4 | J12: 145.7 | K12: 143.2 | L12: 141.8 | M12: 142.5 | N12: =(M12-B12)/B12*100 -> 3.5610465
A13: Vegetables | B13: 132.6 | C13: 143 | D13: 150.5 | E13: 160.3 | F13: 167.4 | G13: 173.2 | H13: 188.4 | I13: 199.6 | J13: 217 | K13: 197 | L13: 170.7 | M13: 157.3 | N13: =(M13-B13)/B13*100 -> 18.627451
A14: Pulses and products | B14: 121.8 | C14: 124.9 | D14: 128.3 | E14: 130 | F14: 130.9 | G14: 131.6 | H14: 132.5 | I14: 135.7 | J14: 138.3 | K14: 140.4 | L14: 141.1 | M14: 141.1 | N14: =(M14-B14)/B14*100 -> 15.845649
A15: Sugar and Confectionery | B15: 109 | C15: 109.9 | D15: 111 | E15: 111.1 | F15: 112 | G15: 113.2 | H15: 114 | I15: 114.2 | J15: 114 | K15: 114.1 | L15: 113.6 | M15: 113.2 | N15: =(M15-B15)/B15*100 -> 3.853211
A16: Spices | B16: 139.5 | C16: 139.9 | D16: 140.6 | E16: 141.7 | F16: 142.6 | G16: 144.1 | H16: 145.4 | I16: 147 | J16: 148.7 | K16: 150.9 | L16: 152 | M16: 153.2 | N16: =(M16-B16)/B16*100 -> 9.8207885
A17: Non-alcoholic beverages | B17: 133.7 | C17: 134 | D17: 134.2 | E17: 134.7 | F17: 134.9 | G17: 135 | H17: 135.1 | I17: 135.3 | J17: 135.8 | K17: 136.1 | L17: 136.5 | M17: 136.7 | N17: =(M17-B17)/B17*100 -> 2.2438295
A18: Prepared meals, snacks, sweets etc. | B18: 155.2 | C18: 155.5 | D18: 155.9 | E18: 156.2 | F18: 156.6 | G18: 156.8 | H18: 157.1 | I18: 157.5 | J18: 158 | K18: 158.6 | L18: 159.1 | M18: 159.6 | N18: =(M18-B18)/B18*100 -> 2.8350515
... A21: Clothing | B21: 147.9 | C21: 148.4 | D21: 148.6 | E21: 148.9 | F21: 149.1 | G21: 149.2 | H21: 149.4 | I21: 149.9 | J21: 150.3 | K21: 150.5 | L21: 150.8 | M21: 151.2 | N21: =(M21-B21)/B21*100 -> 2.2312373
A22: Footwear | B22: 139.9 | C22: 140.4 | D22: 140.4 | E22: 140.5 | F22: 140.6 | G22: 140.6 | H22: 140.8 | I22: 141 | J22: 141.3 | K22: 141.5 | L22: 141.7 | M22: 141.9 | N22: =(M22-B22)/B22*100 -> 1.4295926 | P22: Interpretation
A23: Clothing and footwear | B23: 146.7 | C23: 147.3 | D23: 147.4 | E23: 147.6 | F23: 147.9 | G23: 147.9 | H23: 148.2 | I23: 148.6 | J23: 149 | K23: 149.2 | L23: 149.5 | M23: 149.8 | N23: =(M23-B23)/B23*100 -> 2.1131561 | P23: 1. The CPI inflation (Before March-2020) data in rural+urban sector Eatables Category inflation rate in (7.52%).
A24: Housing | B24: 149 | C24: 150.1 | D24: 149.4 | E24: 150.6 | F24: 151.6 | G24: 152.2 | H24: 153 | I24: 153.5 | J24: 152.8 | K24: 153.9 | L24: 154.8 | M24: 154.5 | N24: =(M24-B24)/B24*100 -> 3.6912752 | P24: 2. The increased inflation rate may be due to weather, supply chain, fuel price hike, input cost, demand and taxation.
A25: Fuel and light | B25: 139.7 | C25: 140.3 | D25: 141.2 | E25: 139.3 | F25: 138.5 | G25: 139.2 | H25: 140.6 | I25: 142.3 | J25: 143.7 | K25: 144.6 | L25: 147.2 | M25: 148.9 | N25: =(M25-B25)/B25*100 -> 6.5855404 | P25: 3.It increases poverty and reduce nutrition, the government needs to act on it efficiently.
A26: Household goods and services | B26: 143.8 | C26: 143.7 | D26: 143.8 | E26: 144.2 | F26: 144.5 | G26: 144.6 | H26: 145 | I26: 145.3 | J26: 145.8 | K26: 146.2 | L26: 146.4 | M26: 146.4 | N26: =(M26-B26)/B26*100 -> 1.8080668 | P26: 4.The government may take action in order to reduce import duties to lower the cost price and increase the number of cold storage houses to preserve the food effectively.
A27: Health | B27: 146.2 | C27: 146.9 | D27: 147.4 | E27: 147.9 | F27: 148.5 | G27: 149 | H27: 149.4 | I27: 149.9 | J27: 150.4 | K27: 151.2 | L27: 151.7 | M27: 152.3 | N27: =(M27-B27)/B27*100 -> 4.1723666
A28: Transport and communication | B28: 124.6 | C28: 124.9 | D28: 124.6 | E28: 125.6 | F28: 125.8 | G28: 126.1 | H28: 126.3 | I28: 126.6 | J28: 129.8 | K28: 130.9 | L28: 130.3 | M28: 129.9 | N28: =(M28-B28)/B28*100 -> 4.2536116
A29: Recreation and amusement | B29: 137.7 | C29: 139.2 | D29: 139.6 | E29: 140.5 | F29: 140.9 | G29: 141.3 | H29: 141.7 | I29: 142.1 | J29: 142.3 | K29: 142.8 | L29: 143.2 | M29: 143.7 | N29: =(M29-B29)/B29*100 -> 4.3572985
A30: Education | B30: 150.3 | C30: 151.6 | D30: 152.5 | E30: 154 | F30: 154.9 | G30: 155.2 | H30: 155.4 | I30: 155.5 | J30: 155.7 | K30: 156.1 | L30: 156.2 | M30: 156.1 | N30: =(M30-B30)/B30*100 -> 3.8589488
A31: Personal care and effects | B31: 133.4 | C31: 133.4 | D31: 134.3 | E31: 135.7 | F31: 138.4 | G31: 139.7 | H31: 140 | I31: 140.3 | J31: 140.4 | K31: 142.3 | L31: 143.4 | M31: 145.2 | N31: =(M31-B31)/B31*100 -> 8.8455772
A32: Miscellaneous | B32: 137.7 | C32: 138.2 | D32: 138.6 | E32: 139.5 | F32: 140.2 | G32: 140.7 | H32: 141 | I32: 141.3 | J32: 142.5 | K32: 143.4 | L32: 143.6 | M32: 143.8 | N32: =(M32-B32)/B32*100 -> 4.4299201
A33: General index | B33: 140.4 | C33: 142 | D33: 142.9 | E33: 144.2 | F33: 145 | G33: 145.8 | H33: 147.2 | I33: 148.6 | J33: 150.4 | K33: 150.2 | L33: 149.1 | M33: 148.6 | N33: =(M33-B33)/B33*100 -> 5.8404558
A34: Eatables | B34: =B19+B18+B17+B16+B15+B14+B13+B12+B11+B10+B9+B8+B7 -> 1762.9 | C34: =C19+C18+C17+C16+C15+C14+C13+C12+C11+C10+C9+C8+C7 -> 1791.9 | D34: =D19+D18+D17+D16+D15+D14+D13+D12+D11+D10+D9+D8+D7 -> 1814.1 | E34: =E19+E18+E17+E16+E15+E14+E13+E12+E11+E10+E9+E8+E7 -> 1837.5 | F34: =F19+F18+F17+F16+F15+F14+F13+F12+F11+F10+F9+F8+F7 -> 1846.5 | G34: =G19+G18+G17+G16+G15+G14+G13+G12+G11+G10+G9+G8+G7 -> 1857.7 | H34: =H19+H18+H17+H16+H15+H14+H13+H12+H11+H10+H9+H8+H7 -> 1885.6 | I34: =I19+I18+I17+I16+I15+I14+I13+I12+I11+I10+I9+I8+I7 -> 1910.9 | ... M34: =M19+M18+M17+M16+M15+M14+M13+M12+M11+M10+M9+M8+M7 -> 1895.4 | N34: =(M34-B34)/B34*100 -> 7.5160247
A35: Apparels | B35: =SUM(B21:B23) -> 434.5 | C35: =SUM(C21:C23) -> 436.1 | D35: =SUM(D21:D23) -> 436.4 | E35: =SUM(E21:E23) -> 437 | F35: =SUM(F21:F23) -> 437.6 | G35: =SUM(G21:G23) -> 437.7 | H35: =SUM(H21:H23) -> 438.4 | I35: =SUM(I21:I23) -> 439.5 | ... M35: =SUM(M21:M23) -> 442.9 | N35: =(M35-B35)/B35*100 -> 1.9332566
A36: Utilities | B36: =SUM(B28,B30,B29) -> 412.6 | C36: =SUM(C28,C30,C29) -> 415.7 | D36: =SUM(D28,D30,D29) -> 416.7 | E36: =SUM(E28,E30,E29) -> 420.1 | F36: =SUM(F28,F30,F29) -> 421.6 | G36: =SUM(G28,G30,G29) -> 422.6 | H36: =SUM(H28,H30,H29) -> 423.4 | I36: =SUM(I28,I30,I29) -> 424.2 | ... M36: =SUM(M28,M30,M29) -> 429.7 | N36: =(M36-B36)/B36*100 -> 4.1444498
A37: Personal Care | B37: =SUM(B27,B31) -> 279.6 | C37: =SUM(C27,C31) -> 280.3 | D37: =SUM(D27,D31) -> 281.7 | E37: =SUM(E27,E31) -> 283.6 | F37: =SUM(F27,F31) -> 286.9 | G37: =SUM(G27,G31) -> 288.7 | H37: =SUM(H27,H31) -> 289.4 | I37: =SUM(I27,I31) -> 290.2 | ... M37: =SUM(M27,M31) -> 297.5 | N37: =(M37-B37)/B37*100 -> 6.4020029
A38: Amenities | B38: =SUM(B24,B25,B26) -> 432.5 | C38: =SUM(C24,C25,C26) -> 434.1 | D38: =SUM(D24,D25,D26) -> 434.4 | E38: =SUM(E24,E25,E26) -> 434.1 | F38: =SUM(F24,F25,F26) -> 434.6 | G38: =SUM(G24,G25,G26) -> 436 | H38: =SUM(H24,H25,H26) -> 438.6 | I38: =SUM(I24,I25,I26) -> 441.1 | ... M38: =SUM(M24,M25,M26) -> 449.8 | N38: =(M38-B38)/B38*100 -> 4
A39: Assorted | B39: =SUM(B32,B20) -> 301.2 | C39: =SUM(C32,C20) -> 302.3 | D39: =SUM(D32,D20) -> 303.5 | E39: =SUM(E32,E20) -> 304.7 | F39: =SUM(F32,F20) -> 306 | G39: =SUM(G32,G20) -> 307.2 | H39: =SUM(H32,H20) -> 308.1 | I39: =SUM(I32,I20) -> 309.2 | ... M39: =SUM(M32,M20) -> 315 | N39: =(M39-B39)/B39*100 -> 4.5816733
A42: Post Pandemic
A44: Year | B44: 2020 | C44: 2020 | D44: 2020 | E44: 2020 | F44: 2020 | G44: 2020 | H44: 2020 | I44: 2020 | J44: 2020 | K44: 2020 | L44: 2021 | M44: 2021 | N44: Inflation Rate %
A45: Month | B45: March | C45: April | D45: May | E45: June | F45: July | G45: August | H45: September | I45: October | J45: November | K45: December | L45: January | M45: February
A46: Cereals and products | B46: 145.1 | C46: 148.7 | D46: 147.7 | E46: 149.6 | F46: 149.6 | G46: 148.9 | H46: 148.4 | I46: 147.5 | J46: 146.8 | K46: 146 | L46: 144.9 | M46: 144.3 | N46: =(M46-B46)/B46*100 -> -0.5513439
A47: Meat and fish | B47: 167 | C47: 184.2 | D47: 184.2 | E47: 192.7 | F47: 192.7 | G47: 190.9 | H47: 187.1 | I47: 188.9 | J47: 191 | K47: 191 | L47: 190.1 | M47: 186.5 | N47: =(M47-B47)/B47*100 -> 11.676647
A48: Egg | B48: 148.1 | C48: 148.8 | D48: 156.7 | E48: 151.4 | F48: 151.4 | G48: 150.8 | H48: 152.5 | I48: 161.4 | J48: 173.6 | K48: 175.3 | L48: 175.3 | M48: 168.7 | N48: =(M48-B48)/B48*100 -> 13.909521
A49: Milk and products | B49: 151.5 | C49: 155.6 | D49: 153 | E49: 153.3 | F49: 153.3 | G49: 153.3 | H49: 153.6 | I49: 153.6 | J49: 153.8 | K49: 154.1 | L49: 154.1 | M49: 154.7 | N49: =(M49-B49)/B49*100 -> 2.1122112
A50: Oils and fats | B50: 131.2 | C50: 135.1 | D50: 136.3 | E50: 136.3 | F50: 136.3 | G50: 137.4 | H50: 138.2 | I50: 140.1 | J50: 142.7 | K50: 146.6 | L50: 150.9 | M50: 158.7 | N50: =(M50-B50)/B50*100 -> 20.960366
A51: Fruits | B51: 142.5 | C51: 149.9 | D51: 147.4 | E51: 147.2 | F51: 147.2 | G51: 150.4 | H51: 150.9 | I51: 151.2 | J51: 148.4 | K51: 147.7 | L51: 149.6 | M51: 150.7 | N51: =(M51-B51)/B51*100 -> 5.754386
A52: Vegetables | B52: 157.3 | C52: 168.6 | D52: 187.7 | E52: 156.5 | F52: 156.5 | G52: 178.1 | H52: 186.7 | I52: 209.2 | J52: 230 | K52: 230.5 | L52: 194.2 | M52: 160 | N52: =(M52-B52)/B52*100 -> 1.7164654
A53: Pulses and products | B53: 141.1 | C53: 150.4 | D53: 149.4 | E53: 150.9 | F53: 150.9 | G53: 150.4 | H53: 149.8 | I53: 150.9 | J53: 156.8 | K53: 160.2 | L53: 160.4 | M53: 158.8 | N53: =(M53-B53)/B53*100 -> 12.544295
A54: Sugar and Confectionery | B54: 113.2 | C54: 120.3 | D54: 115.6 | E54: 114.2 | F54: 114.2 | G54: 115.1 | H54: 116.4 | I54: 116.2 | J54: 115.7 | K54: 115.3 | L54: 114.6 | M54: 112.8 | N54: =(M54-B54)/B54*100 -> -0.35335689
A55: Spices | B55: 153.2 | C55: 157.1 | D55: 157.9 | E55: 159.5 | F55: 159.5 | G55: 160 | H55: 160.3 | I55: 161 | J55: 161.8 | K55: 163 | L55: 164 | M55: 164.2 | N55: =(M55-B55)/B55*100 -> 7.1801567
A56: Non-alcoholic beverages | B56: 136.7 | C56: 136.8 | D56: 140.12 | E56: 139.4 | F56: 139.4 | G56: 140.6 | H56: 142.2 | I56: 144 | J56: 146.5 | K56: 149.2 | L56: 151.8 | M56: 155.5 | N56: =(M56-B56)/B56*100 -> 13.752743
A57: Prepared meals, snacks, sweets etc. | B57: 159.6 | C57: 161.8 | D57: 161.8 | E57: 161.8 | F57: 161.8 | G57: 162.3 | H57: 162.9 | I57: 163.2 | J57: 163.8 | K57: 164.8 | L57: 165.6 | M57: 167.5 | N57: =(M57-B57)/B57*100 -> 4.9498747
... A60: Clothing | B60: 151.2 | C60: 152.3 | D60: 152.3 | E60: 152.5 | F60: 152.5 | G60: 153.1 | H60: 153.4 | I60: 153.7 | J60: 154.3 | K60: 155 | L60: 155.5 | M60: 157.2 | N60: =(M60-B60)/B60*100 -> 3.968254
A61: Footwear | B61: 141.9 | C61: 142.9 | D61: 142.9 | E61: 144.4 | F61: 144.4 | G61: 143.4 | H61: 144.3 | I61: 144.6 | J61: 144.9 | K61: 145.4 | L61: 146.1 | M61: 147.4 | N61: =(M61-B61)/B61*100 -> 3.875969 | P61: Interpretation
A62: Clothing and footwear | B62: 149.8 | C62: 150.9 | D62: 150.9 | E62: 151.4 | F62: 151.4 | G62: 151.7 | H62: 152 | I62: 152.3 | J62: 152.8 | K62: 153.6 | L62: 154.2 | M62: 155.8 | N62: =(M62-B62)/B62*100 -> 4.0053405 | P62: 1. The CPI inflation (post March-2020) data in rural+urban sector Assorted Category inflation rate in (8.48%).
A63: Housing | B63: 154.5 | C63: 155.6 | D63: 139.3 | E63: 154.7 | F63: 154.7 | G63: 155.5 | H63: 156.3 | I63: 156.5 | J63: 158 | K63: 158.4 | L63: 157.7 | M63: 159.8 | N63: =(M63-B63)/B63*100 -> 3.4304207 | P63: 2. The increased inflation rate may be because of restriction free consumption, peer pressure, depression and anxiety post Pandemic.
A64: Fuel and light | B64: 148.9 | C64: 144.1 | D64: 143.3 | E64: 141.9 | F64: 141.9 | G64: 143 | H64: 142.9 | I64: 143.1 | J64: 143.6 | K64: 144.6 | L64: 147.9 | M64: 152.4 | N64: =(M64-B64)/B64*100 -> 2.3505709 | P64: 3.The government may take action to reduce the usage of these stuffs by increasing taxes, raising awareness, strict Regulation formulation.
A65: Household goods and services | B65: 146.4 | C65: 147.5 | D65: 147.5 | E65: 146.4 | F65: 146.4 | G65: 148.4 | H65: 148.7 | I65: 148.7 | J65: 149.2 | K65: 149.7 | L65: 150 | M65: 150.9 | N65: =(M65-B65)/B65*100 -> 3.0737705
A66: Health | B66: 152.3 | C66: 150.7 | D66: 153.5 | E66: 154.4 | F66: 154.4 | G66: 155 | H66: 155.6 | I66: 156.3 | J66: 157.2 | K66: 158.3 | L66: 159.3 | M66: 161.3 | N66: =(M66-B66)/B66*100 -> 5.9093894
A67: Transport and communication | B67: 129.9 | C67: 136.3 | D67: 136.3 | E67: 135 | F67: 135 | G67: 138.5 | H67: 139.6 | I67: 140.6 | J67: 140.4 | K67: 140.7 | L67: 141.9 | M67: 145.1 | N67: =(M67-B67)/B67*100 -> 11.701309
A68: Recreation and amusement | B68: 143.7 | C68: 146.7 | D68: 146.7 | E68: 148.3 | F68: 148.3 | G68: 146 | H68: 146.6 | I68: 146.5 | J68: 148.4 | K68: 148.5 | L68: 149.6 | M68: 151.5 | N68: =(M68-B68)/B68*100 -> 5.4279749
A69: Education | B69: 156.1 | C69: 157.8 | D69: 157.8 | E69: 156.4 | F69: 156.4 | G69: 158.5 | H69: 157.5 | I69: 158.5 | J69: 158.6 | K69: 159.4 | L69: 159.2 | M69: 159.5 | N69: =(M69-B69)/B69*100 -> 2.178091
A70: Personal care and effects | B70: 145.2 | C70: 151.8 | D70: 151.8 | E70: 151.6 | F70: 151.6 | G70: 154.3 | H70: 158.4 | I70: 157 | J70: 156.9 | K70: 157.1 | L70: 156.8 | M70: 155.8 | N70: =(M70-B70)/B70*100 -> 7.3002755
A71: Miscellaneous | B71: 143.8 | C71: 147.5 | D71: 147.5 | E71: 147 | F71: 147 | G71: 149 | H71: 150 | I71: 150.4 | J71: 150.7 | K71: 151.2 | L71: 151.9 | M71: 153.4 | N71: =(M71-B71)/B71*100 -> 6.6759388
A72: General index | B72: 148.6 | C72: 153.3 | D72: 153.3 | E72: 151.8 | F72: 151.8 | G72: 153.9 | H72: 154.7 | I72: 156.4 | J72: 158.4 | K72: 158.9 | L72: 157.3 | M72: 156.6 | N72: =(M72-B72)/B72*100 -> 5.3835801
A73: Eatables | B73: =B58+B57+B56+B55+B54+B53+B52+B51+B50+B49+B48+B47+B46 -> 1895.4 | C73: =C58+C57+C56+C55+C54+C53+C52+C51+C50+C49+C48+C47+C46 -> 1968.7 | D73: =D58+D57+D56+D55+D54+D53+D52+D51+D50+D49+D48+D47+D46 -> 1994.42 | E73: =E58+E57+E56+E55+E54+E53+E52+E51+E50+E49+E48+E47+E46 -> 1966.8 | F73: =F58+F57+F56+F55+F54+F53+F52+F51+F50+F49+F48+F47+F46 -> 1966.8 | G73: =G58+G57+G56+G55+G54+G53+G52+G51+G50+G49+G48+G47+G46 -> 1995.2 | H73: =H58+H57+H56+H55+H54+H53+H52+H51+H50+H49+H48+H47+H46 -> 2007 | I73: =I58+I57+I56+I55+I54+I53+I52+I51+I50+I49+I48+I47+I46 -> 2048.6 | ... M73: =M58+M57+M56+M55+M54+M53+M52+M51+M50+M49+M48+M47+M46 -> 2039.3 | N73: =(M73-B73)/B73*100 -> 7.592065
A74: Apparels | B74: =SUM(B60:B62) -> 442.9 | C74: =SUM(C60:C62) -> 446.1 | D74: =SUM(D60:D62) -> 446.1 | E74: =SUM(E60:E62) -> 448.3 | F74: =SUM(F60:F62) -> 448.3 | G74: =SUM(G60:G62) -> 448.2 | H74: =SUM(H60:H62) -> 449.7 | I74: =SUM(I60:I62) -> 450.6 | ... M74: =SUM(M60:M62) -> 460.4 | N74: =(M74-B74)/B74*100 -> 3.9512305
A75: Utilities | B75: =SUM(B67,B69,B68) -> 429.7 | C75: =SUM(C67,C69,C68) -> 440.8 | D75: =SUM(D67,D69,D68) -> 440.8 | E75: =SUM(E67,E69,E68) -> 439.7 | F75: =SUM(F67,F69,F68) -> 439.7 | G75: =SUM(G67,G69,G68) -> 443 | H75: =SUM(H67,H69,H68) -> 443.7 | I75: =SUM(I67,I69,I68) -> 445.6 | ... M75: =SUM(M67,M69,M68) -> 456.1 | N75: =(M75-B75)/B75*100 -> 6.1438213
A76: Personal Care | B76: =SUM(B66,B70) -> 297.5 | C76: =SUM(C66,C70) -> 302.5 | D76: =SUM(D66,D70) -> 305.3 | E76: =SUM(E66,E70) -> 306 | F76: =SUM(F66,F70) -> 306 | G76: =SUM(G66,G70) -> 309.3 | H76: =SUM(H66,H70) -> 314 | I76: =SUM(I66,I70) -> 313.3 | ... M76: =SUM(M66,M70) -> 317.1 | N76: =(M76-B76)/B76*100 -> 6.5882353
A77: Amenities | B77: =SUM(B63,B64,B65) -> 449.8 | C77: =SUM(C63,C64,C65) -> 447.2 | D77: =SUM(D63,D64,D65) -> 430.1 | E77: =SUM(E63,E64,E65) -> 443 | F77: =SUM(F63,F64,F65) -> 443 | G77: =SUM(G63,G64,G65) -> 446.9 | H77: =SUM(H63,H64,H65) -> 447.9 | I77: =SUM(I63,I64,I65) -> 448.3 | ... M77: =SUM(M63,M64,M65) -> 463.1 | N77: =(M77-B77)/B77*100 -> 2.9568697
A78: Assorted | B78: =SUM(B71,B59) -> 315 | C78: =SUM(C71,C59) -> 328.1 | D78: =SUM(D71,D59) -> 328.1 | E78: =SUM(E71,E59) -> 330.5 | F78: =SUM(F71,F59) -> 330.5 | G78: =SUM(G71,G59) -> 331.6 | H78: =SUM(H71,H59) -> 334.4 | I78: =SUM(I71,I59) -> 334.7 | ... M78: =SUM(M71,M59) -> 341.7 | N78: =(M78-B78)/B78*100 -> 8.4761905

Sheet PS_5
A1: Impact of Imported Oil Price on Inflation Rates(Sector-Rural+Urban)
A3: Year | B3: 2021 | C3: 2021 | D3: 2021 | E3: 2021 | F3: 2021 | G3: 2021 | H3: 2021 | I3: 2021 | J3: 2021 | K3: 2021 | L3: 2021 | M3: 2021 | N3: 2022 | O3: 2022 | P3: 2022 | Q3: 2022 | R3: 2022 | S3: 2022 | T3: 2022 | U3: 2022 | V3: 2022 | W3: 2022 | X3: 2022 | Y3: 2022 | Z3: 2023 | AA3: 2023 | AB3: 2023 | AC3: 2023 | AD3: 2023 | AE3: Correlation
A4: Month | B4: January | C4: February | D4: March | E4: April | F4: May | G4: June | H4: July | I4: August | J4: September | K4: October | L4: November | M4: December | N4: January | O4: February | P4: March | Q4: April | R4: May | S4: June | T4: July | U4: August | V4: September | W4: October | X4: November | Y4: December | Z4: January | AA4: February | AB4: March | AC4: April | AD4: May
A5: Crude Oil Price | B5: 66695.479 | C5: 60965.591 | D5: 75470.774 | E5: 74207.645 | F5: 70046.397 | G5: 71679.349 | H5: 72860.439 | I5: 80983.016 | J5: 83035.174 | K5: 91471.514 | L5: 95105.452 | M5: 100380.53 | N5: 101828.29 | O5: 102317.69 | P5: 134181.48 | Q5: 151257.78 | R5: 137781.52 | S5: 140362 | T5: 148619.35 | U5: 120976.19 | V5: 110015.88 | W5: 116548.2 | X5: 118277.28 | Y5: 112095.48 | Z5: 108892.97 | AA5: 103743.51 | AB5: 107655.66 | AC5: 101210.18 | AD5: 103486.67
A6: Cereals and products | B6: 144.9 | C6: 144.3 | D6: 144.1 | E6: 144.3 | F6: 146.3 | G6: 146.7 | H6: 146.4 | I6: 146.6 | J6: 146.6 | K6: 147.4 | L6: 148.2 | M6: 148.7 | N6: 149.5 | O6: 150 | P6: 151.3 | Q6: 152.9 | R6: 154.1 | S6: 155 | T6: 156.5 | U6: 160.3 | V6: 163.5 | W6: 165.2 | X6: 167.4 | Y6: 169.2 | Z6: 173.8 | AA6: 174.4 | AB6: 174.4 | AC6: 173.8 | AD6: 173.7 | AE6: =CORREL($B$5:$AD$5,B6:AD6) -> 0.43987123
A7: Meat and fish | B7: 190.1 | C7: 186.5 | D7: 192.2 | E7: 198 | F7: 200.5 | G7: 202 | H7: 206.8 | I7: 204 | J7: 204 | K7: 204.6 | L7: 201.6 | M7: 198.8 | N7: 198.7 | O7: 200.6 | P7: 210.7 | Q7: 211.8 | R7: 217 | S7: 219.4 | T7: 213 | U7: 206.5 | V7: 209.2 | W7: 210.9 | X7: 209.4 | Y7: 209 | Z7: 210.7 | AA7: 207.7 | AB7: 207.7 | AC7: 209.3 | AD7: 214.3 | AE7: =CORREL($B$5:$AD$5,B7:AD7) -> 0.79268302 | AF7: Most Positively Affected
A8: Egg | B8: 175.3 | C8: 168.7 | D8: 163.8 | E8: 164.6 | F8: 170.3 | G8: 180.7 | H8: 182.2 | I8: 172.8 | J8: 172.8 | K8: 171.2 | L8: 173 | M8: 177.9 | N8: 178.8 | O8: 175.8 | P8: 167.8 | Q8: 164.5 | R8: 162.4 | S8: 170.8 | T8: 175.2 | U8: 169.2 | V8: 169.7 | W8: 170.9 | X8: 181.4 | Y8: 190.2 | Z8: 194.5 | AA8: 175.2 | AB8: 175.2 | AC8: 169.6 | AD8: 173.2 | AE8: =CORREL($B$5:$AD$5,B8:AD8) -> -0.083046591 | AF8: Negatively Affected
A9: Milk and products | B9: 154.1 | C9: 154.7 | D9: 154.9 | E9: 155.4 | F9: 156.1 | G9: 156.2 | H9: 157.5 | I9: 158.4 | J9: 158.4 | K9: 158.7 | L9: 159.3 | M9: 159.9 | N9: 160.5 | O9: 160.7 | P9: 162.2 | Q9: 163.9 | R9: 164.9 | S9: 165.8 | T9: 166.6 | U9: 168.1 | V9: 169.7 | W9: 170.9 | X9: 172.3 | Y9: 173.6 | Z9: 174.6 | AA9: 177.3 | AB9: 177.3 | AC9: 178.4 | AD9: 179.5 | AE9: =CORREL($B$5:$AD$5,B9:AD9) -> 0.52771328
A10: Oils and fats | B10: 150.9 | C10: 158.7 | D10: 163.9 | E10: 170.1 | F10: 178.7 | G10: 183.7 | H10: 182.1 | I10: 188 | J10: 188 | K10: 190.6 | L10: 190.1 | M10: 187.6 | N10: 184.7 | O10: 184.9 | P10: 194.6 | Q10: 199.5 | R10: 202.4 | S10: 200.9 | T10: 195.8 | U10: 192.4 | V10: 188.7 | W10: 186.5 | X10: 188.9 | Y10: 188.5 | Z10: 187.2 | AA10: 179.3 | AB10: 179.2 | AC10: 174.9 | AD10: 170 | AE10: =CORREL($B$5:$AD$5,B10:AD10) -> 0.7514291
A11: Fruits | B11: 149.6 | C11: 150.7 | D11: 153.7 | E11: 164.4 | F11: 167.1 | G11: 164.6 | H11: 163.9 | I11: 156.8 | J11: 156.7 | K11: 155.7 | L11: 156.5 | M11: 154.9 | N11: 153.7 | O11: 153.7 | P11: 157.6 | Q11: 172.6 | R11: 171 | S11: 169.7 | T11: 174.2 | U11: 172.9 | V11: 165.7 | W11: 163.8 | X11: 160.7 | Y11: 158 | Z11: 158.3 | AA11: 169.5 | AB11: 169.5 | AC11: 176.3 | AD11: 172.2 | AE11: =CORREL($B$5:$AD$5,B11:AD11) -> 0.52538853
A12: Vegetables | B12: 194.2 | C12: 160 | D12: 149.5 | E12: 144.1 | F12: 147.9 | G12: 155.4 | H12: 164.2 | I12: 162.2 | J12: 162.3 | K12: 185.3 | L12: 199.2 | M12: 188.3 | N12: 174.3 | O12: 169.7 | P12: 166.9 | Q12: 166.2 | R12: 174.9 | S12: 182.3 | T12: 182.1 | U12: 186.7 | V12: 191.8 | W12: 199.7 | X12: 183.1 | Y12: 159.9 | Z12: 153.9 | AA12: 152.7 | AB12: 152.8 | AC12: 155.4 | AD12: 161 | AE12: =CORREL($B$5:$AD$5,B12:AD12) -> 0.32872483
A13: Pulses and products | B13: 160.4 | C13: 158.8 | D13: 159.8 | E13: 161.7 | F13: 165.4 | G13: 166 | H13: 164 | I13: 164.1 | J13: 164.1 | K13: 165.2 | L13: 165.3 | M13: 164.4 | N13: 163.9 | O13: 163.7 | P13: 163.9 | Q13: 164.7 | R13: 164.7 | S13: 164.3 | T13: 164.3 | U13: 167.2 | V13: 169.1 | W13: 169.8 | X13: 170.5 | Y13: 170.8 | Z13: 170.9 | AA13: 171 | AB13: 171.1 | AC13: 173.4 | AD13: 175.6 | AE13: =CORREL($B$5:$AD$5,B13:AD13) -> 0.32248817
A14: Sugar and Confectionery | B14: 114.6 | C14: 112.8 | D14: 112.6 | E14: 113.1 | F14: 114.8 | G14: 115.1 | H14: 114.5 | I14: 119.7 | J14: 119.7 | K14: 121.9 | L14: 122.4 | M14: 121 | N14: 120 | O14: 118.9 | P14: 118.8 | Q14: 119 | R14: 119.7 | S14: 119.9 | T14: 120 | U14: 120.9 | V14: 121.6 | W14: 121.9 | X14: 122.1 | Y14: 121.8 | Z14: 121.1 | AA14: 120 | AB14: 120 | AC14: 121.3 | AD14: 122.7 | AE14: =CORREL($B$5:$AD$5,B14:AD14) -> 0.60891819
A15: Spices | B15: 164 | C15: 164.2 | D15: 163.5 | E15: 163.9 | F15: 168.2 | G15: 168.5 | H15: 168.3 | I15: 168.8 | J15: 168.8 | K15: 169.3 | L15: 169.6 | M15: 170.5 | N15: 172.1 | O15: 174.3 | P15: 177.4 | Q15: 181.3 | R15: 184.9 | S15: 187.1 | T15: 190 | U15: 193.6 | V15: 197.3 | W15: 199.9 | X15: 202.8 | Y15: 205.2 | Z15: 208.4 | AA15: 209.7 | AB15: 209.7 | AC15: 212.9 | AD15: 218 | AE15: =CORREL($B$5:$AD$5,B15:AD15) -> 0.51227602
A16: Non-alcoholic beverages | B16: 151.8 | C16: 155.5 | D16: 156.5 | E16: 157.6 | F16: 159.3 | G16: 160 | H16: 160.9 | I16: 162.7 | J16: 162.7 | K16: 163.2 | L16: 163.7 | M16: 164.2 | N16: 164.3 | O16: 164.7 | P16: 165.3 | Q16: 166.2 | R16: 167.1 | S16: 167.9 | T16: 168.4 | U16: 168.8 | V16: 169.4 | W16: 169.9 | X16: 170.4 | Y16: 171 | Z16: 171.4 | AA16: 172.3 | AB16: 172.3 | AC16: 172.9 | AD16: 173.4 | AE16: =CORREL($B$5:$AD$5,B16:AD16) -> 0.67563173
A17: Prepared meals, snacks, sweets etc. | B17: 165.6 | C17: 167.5 | D17: 168.2 | E17: 168.9 | F17: 170.4 | G17: 172.4 | H17: 172.2 | I17: 173.9 | J17: 173.9 | K17: 174.7 | L17: 175.5 | M17: 176.5 | N17: 177.3 | O17: 178 | P17: 179.3 | Q17: 180.9 | R17: 182.5 | S17: 183.9 | T17: 185.2 | U17: 186.3 | V17: 187.4 | W17: 188.3 | X17: 189.5 | Y17: 190.3 | Z17: 191.2 | AA17: 193 | AB17: 193 | AC17: 193.5 | AD17: 194.2 | AE17: =CORREL($B$5:$AD$5,B17:AD17) -> 0.63528538
A18: Food and beverages | B18: 161 | C18: 156.9 | D18: 156.7 | E18: 158 | F18: 160.7 | G18: 162.6 | H18: 164 | I18: 164 | J18: 164 | K18: 167.7 | L18: 169.7 | M18: 168.2 | N18: 166.4 | O18: 166.2 | P18: 168.4 | Q18: 170.8 | R18: 173.3 | S18: 174.9 | T18: 175 | U18: 176.3 | V18: 177.8 | W18: 179.6 | X18: 178.3 | Y18: 175.9 | Z18: 176.7 | AA18: 177 | AB18: 177 | AC18: 177.9 | AD18: 179.1 | AE18: =CORREL($B$5:$AD$5,B18:AD18) -> 0.70967053
A19: Pan, tobacco and intoxicants | B19: 186.5 | C19: 188.3 | D19: 188.1 | E19: 188.8 | F19: 191.9 | G19: 190.8 | H19: 191.2 | I19: 192.1 | J19: 192.1 | K19: 192.7 | L19: 192.9 | M19: 192.4 | N19: 192.2 | O19: 192.8 | P19: 193.7 | Q19: 193.9 | R19: 194.1 | S19: 194.3 | T19: 194.6 | U19: 195 | V19: 195.9 | W19: 196.3 | X19: 196.9 | Y19: 197.3 | Z19: 198.2 | AA19: 199.5 | AB19: 199.5 | AC19: 200.6 | AD19: 201 | AE19: =CORREL($B$5:$AD$5,B19:AD19) -> 0.53225538
A20: Clothing | B20: 155.5 | C20: 157.2 | D20: 157.8 | E20: 158.8 | F20: 161.8 | G20: 162.2 | H20: 162.8 | I20: 164.5 | J20: 164.6 | K20: 165.7 | L20: 167.2 | M20: 168.5 | N20: 169.9 | O20: 170.8 | P20: 172.1 | Q20: 173.9 | R20: 175.6 | S20: 177.1 | T20: 178.3 | U20: 179.5 | V20: 180.9 | W20: 181.9 | X20: 183.1 | Y20: 184 | Z20: 184.9 | AA20: 186.2 | AB20: 186.1 | AC20: 186.9 | AD20: 187.3 | AE20: =CORREL($B$5:$AD$5,B20:AD20) -> 0.66726193 | AH20: INTERPRETATION
A21: Footwear | B21: 146.1 | C21: 147.4 | D21: 147.9 | E21: 148.5 | F21: 152.1 | G21: 151.8 | H21: 153.1 | I21: 155.3 | J21: 155.3 | K21: 156.3 | L21: 157.4 | M21: 158.7 | N21: 160.7 | O21: 162.4 | P21: 164.6 | Q21: 166.5 | R21: 168.4 | S21: 169.9 | T21: 171.3 | U21: 172.7 | V21: 174.3 | W21: 175.3 | X21: 176.2 | Y21: 177 | Z21: 177.6 | AA21: 178.7 | AB21: 178.7 | AC21: 179.2 | AD21: 179.7 | AE21: =CORREL($B$5:$AD$5,B21:AD21) -> 0.69238472 | AH21: 1. The CPI inflation data in rural+urban sector the Crude oil price change with high change
A22: Clothing and footwear | B22: 154.2 | C22: 155.8 | D22: 156.4 | E22: 157.3 | F22: 160.4 | G22: 160.7 | H22: 161.4 | I22: 163.2 | J22: 163.3 | K22: 164.3 | L22: 165.8 | M22: 167 | N22: 168.5 | O22: 169.6 | P22: 171.1 | Q22: 172.8 | R22: 174.6 | S22: 176 | T22: 177.3 | U22: 178.5 | V22: 179.9 | W22: 181 | X22: 182.1 | Y22: 183 | Z22: 183.8 | AA22: 185.1 | AB22: 185.1 | AC22: 185.7 | AD22: 186.2 | AE22: =CORREL($B$5:$AD$5,B22:AD22) -> 0.67151997 | AH22: the inflation Meat and Fish Category(0.79%) as compare to other categorise.
A23: Housing | B23: 157.7 | C23: 159.8 | D23: 159.9 | E23: 161.4 | F23: 161.6 | G23: 160.5 | H23: 161.5 | I23: 162.1 | J23: 162.1 | K23: 163.6 | L23: 164.2 | M23: 163.4 | N23: 164.5 | O23: 165.5 | P23: 165.3 | Q23: 167 | R23: 167.5 | S23: 166.8 | T23: 167.8 | U23: 169 | V23: 169.5 | W23: 171.2 | X23: 171.8 | Y23: 170.7 | Z23: 172.1 | AA23: 173.5 | AB23: 173.5 | AC23: 175.2 | AD23: 175.6 | AE23: =CORREL($B$5:$AD$5,B23:AD23) -> 0.58260754 | AH23: 2.The crude oil price change with second high change the inflation Transport
A24: Fuel and light | B24: 147.9 | C24: 152.4 | D24: 155.5 | E24: 155.6 | F24: 159.4 | G24: 159.8 | H24: 160.7 | I24: 162.6 | J24: 162.6 | K24: 164.2 | L24: 163.9 | M24: 164.1 | N24: 164.2 | O24: 165.7 | P24: 167.2 | Q24: 172.2 | R24: 174.6 | S24: 176 | T24: 179.6 | U24: 178.8 | V24: 179.5 | W24: 180.5 | X24: 181.3 | Y24: 182 | Z24: 182 | AA24: 182.1 | AB24: 181.9 | AC24: 181.7 | AD24: 182.8 | AE24: =CORREL($B$5:$AD$5,B24:AD24) -> 0.71027193 | AH24: and Communication Category (0.78%).
A25: Household goods and services | B25: 150 | C25: 150.9 | D25: 151.2 | E25: 151.8 | F25: 154.7 | G25: 154.8 | H25: 155.8 | I25: 157.5 | J25: 157.5 | K25: 158.4 | L25: 159.3 | M25: 160.2 | N25: 161.1 | O25: 161.8 | P25: 162.8 | Q25: 164 | R25: 165.2 | S25: 166.4 | T25: 167.4 | U25: 168.5 | V25: 169.5 | W25: 170.4 | X25: 171.4 | Y25: 172.1 | Z25: 172.9 | AA25: 174.2 | AB25: 174.2 | AC25: 174.6 | AD25: 175.2 | AE25: =CORREL($B$5:$AD$5,B25:AD25) -> 0.65422152
A26: Health | B26: 159.3 | C26: 161.3 | D26: 161.7 | E26: 162.3 | F26: 165.8 | G26: 166.3 | H26: 167 | I26: 168.4 | J26: 168.4 | K26: 169.1 | L26: 169.9 | M26: 170.6 | N26: 171.4 | O26: 172.2 | P26: 173 | Q26: 174 | R26: 174.8 | S26: 175.4 | T26: 176.1 | U26: 176.8 | V26: 177.8 | W26: 178.7 | X26: 179.8 | Y26: 181.1 | Z26: 182.3 | AA26: 184.4 | AB26: 184.4 | AC26: 185 | AD26: 185.7 | AE26: =CORREL($B$5:$AD$5,B26:AD26) -> 0.61833742
A27: Transport and communication | B27: 141.9 | C27: 145.1 | D27: 146.2 | E27: 146.6 | F27: 148.9 | G27: 150.7 | H27: 153.1 | I27: 154 | J27: 154 | K27: 155.7 | L27: 154.8 | M27: 155.7 | N27: 156.5 | O27: 156.9 | P27: 157.9 | Q27: 162.6 | R27: 163 | S27: 161.1 | T27: 161.6 | U27: 161.9 | V27: 162.3 | W27: 162.9 | X27: 163 | Y27: 163.4 | Z27: 163.6 | AA27: 164.2 | AB27: 164.2 | AC27: 164.5 | AD27: 164.8 | AE27: =CORREL($B$5:$AD$5,B27:AD27) -> 0.77857772
A28: Recreation and amusement | B28: 149.6 | C28: 151.5 | D28: 152.6 | E28: 153.2 | F28: 155.8 | G28: 154.9 | H28: 155.3 | I28: 157.6 | J28: 157.7 | K28: 158.6 | L28: 159.8 | M28: 160.6 | N28: 161.2 | O28: 162.1 | P28: 163.3 | Q28: 164.4 | R28: 165.1 | S28: 165.8 | T28: 166.3 | U28: 166.9 | V28: 167.6 | W28: 168.2 | X28: 168.5 | Y28: 168.9 | Z28: 169.5 | AA28: 170.3 | AB28: 170.3 | AC28: 170.7 | AD28: 171.2 | AE28: =CORREL($B$5:$AD$5,B28:AD28) -> 0.72403484
A29: Education | B29: 159.2 | C29: 159.5 | D29: 160.2 | E29: 160.3 | F29: 161.2 | G29: 161.7 | H29: 163.2 | I29: 163.8 | J29: 163.7 | K29: 163.9 | L29: 164.3 | M29: 164.4 | N29: 164.7 | O29: 165.4 | P29: 166 | Q29: 166.9 | R29: 167.9 | S29: 169 | T29: 171.4 | U29: 172.3 | V29: 173.1 | W29: 173.4 | X29: 173.7 | Y29: 174.1 | Z29: 174.3 | AA29: 175 | AB29: 175 | AC29: 176.4 | AD29: 177.1 | AE29: =CORREL($B$5:$AD$5,B29:AD29) -> 0.59613395
A30: Personal care and effects | B30: 156.8 | C30: 155.8 | D30: 153.8 | E30: 155.4 | F30: 158.6 | G30: 158.8 | H30: 160.1 | I30: 160 | J30: 160 | K30: 160.8 | L30: 162.2 | M30: 162.6 | N30: 163 | O30: 164.4 | P30: 167.2 | Q30: 168.8 | R30: 168.4 | S30: 169.4 | T30: 169.7 | U30: 171.2 | V30: 170.9 | W30: 172.1 | X30: 173.6 | Y30: 175.8 | Z30: 178.6 | AA30: 181 | AB30: 181 | AC30: 184 | AD30: 185.2 | AE30: =CORREL($B$5:$AD$5,B30:AD30) -> 0.55910185 | AH30: RECOMANDATION
A31: Miscellaneous | B31: 151.9 | C31: 153.4 | D31: 153.8 | E31: 154.4 | F31: 156.8 | G31: 157.6 | H31: 159 | I31: 160 | J31: 160 | K31: 161 | L31: 161.4 | M31: 162 | N31: 162.7 | O31: 163.5 | P31: 164.6 | Q31: 166.8 | R31: 167.5 | S31: 167.5 | T31: 168.4 | U31: 169.1 | V31: 169.7 | W31: 170.5 | X31: 171.1 | Y31: 172 | Z31: 172.8 | AA31: 174.1 | AB31: 174.1 | AC31: 175 | AD31: 175.7 | AE31: =CORREL($B$5:$AD$5,B31:AD31) -> 0.67548161 | AH31: Food & beverages contribute the largest share to CPI | AI31: :- Expand buffer stock management for cereals and pulses
A32: General index | B32: 157.3 | C32: 156.6 | D32: 156.8 | E32: 157.8 | F32: 160.4 | G32: 161.3 | H32: 162.5 | I32: 163.2 | J32: 163.2 | K32: 165.5 | L32: 166.7 | M32: 166.2 | N32: 165.7 | O32: 166.1 | P32: 167.7 | Q32: 170.1 | R32: 171.7 | S32: 172.6 | T32: 173.4 | U32: 174.3 | V32: 175.3 | W32: 176.7 | X32: 176.5 | Y32: 175.7 | Z32: 176.5 | AA32: 177.2 | AB32: 177.2 | AC32: 178.1 | AD32: 179.1 | AE32: =CORREL($B$5:$AD$5,B32:AD32) -> 0.69517096 | AI32: Improve cold storage and warehousing for perishable food items
A33: Eatables | B33: =B18+B17+B16+B15+B14+B13+B12+B11+B10+B9+B8+B7+B6 -> 2076.5 | C33: =C18+C17+C16+C15+C14+C13+C12+C11+C10+C9+C8+C7+C6 -> 2039.3 | D33: =D18+D17+D16+D15+D14+D13+D12+D11+D10+D9+D8+D7+D6 -> 2039.4 | E33: =E18+E17+E16+E15+E14+E13+E12+E11+E10+E9+E8+E7+E6 -> 2064.1 | F33: =F18+F17+F16+F15+F14+F13+F12+F11+F10+F9+F8+F7+F6 -> 2105.7 | G33: =G18+G17+G16+G15+G14+G13+G12+G11+G10+G9+G8+G7+G6 -> 2133.9 | H33: =H18+H17+H16+H15+H14+H13+H12+H11+H10+H9+H8+H7+H6 -> 2147 | I33: =I18+I17+I16+I15+I14+I13+I12+I11+I10+I9+I8+I7+I6 -> 2142 | ... AD33: =AD18+AD17+AD16+AD15+AD14+AD13+AD12+AD11+AD10+AD9+AD8+AD7+AD6 -> 2306.9 | AE33: =CORREL($B$5:$AD$5,B33:AD33) -> 0.71355462 | AI33: Reduce inter-state movement restrictions during supply shocks
A34: Apparels | B34: =SUM(B20:B22) -> 455.8 | C34: =SUM(C20:C22) -> 460.4 | D34: =SUM(D20:D22) -> 462.1 | E34: =SUM(E20:E22) -> 464.6 | F34: =SUM(F20:F22) -> 474.3 | G34: =SUM(G20:G22) -> 474.7 | H34: =SUM(H20:H22) -> 477.3 | I34: =SUM(I20:I22) -> 483 | ... AD34: =SUM(AD20:AD22) -> 553.2 | AE34: =CORREL($B$5:$AD$5,B34:AD34) -> 0.67778614 | AH34: Strong correlation between imported crude oil prices and CPI | AI34: :-Create a fuel price smoothing fund,Adjust excise duties dynamically during global oil shocks
A35: Utilities | B35: =SUM(B27,B29,B28) -> 450.7 | C35: =SUM(C27,C29,C28) -> 456.1 | D35: =SUM(D27,D29,D28) -> 459 | E35: =SUM(E27,E29,E28) -> 460.1 | F35: =SUM(F27,F29,F28) -> 465.9 | G35: =SUM(G27,G29,G28) -> 467.3 | H35: =SUM(H27,H29,H28) -> 471.6 | I35: =SUM(I27,I29,I28) -> 475.4 | ... AD35: =SUM(AD27,AD29,AD28) -> 513.1 | AE35: =CORREL($B$5:$AD$5,B35:AD35) -> 0.71503702
A36: Personal Care | B36: =SUM(B26,B30) -> 316.1 | C36: =SUM(C26,C30) -> 317.1 | D36: =SUM(D26,D30) -> 315.5 | E36: =SUM(E26,E30) -> 317.7 | F36: =SUM(F26,F30) -> 324.4 | G36: =SUM(G26,G30) -> 325.1 | H36: =SUM(H26,H30) -> 327.1 | I36: =SUM(I26,I30) -> 328.4 | ... AD36: =SUM(AD26,AD30) -> 370.9 | AE36: =CORREL($B$5:$AD$5,B36:AD36) -> 0.58923704 | AH36: Healthcare inflation increased post-COVID | AI36: :Monitor private healthcare pricing,Expand public healthcare capacity,Promote generic medicine adoption
A37: Amenities | B37: =SUM(B23,B24,B25) -> 455.6 | C37: =SUM(C23,C24,C25) -> 463.1 | D37: =SUM(D23,D24,D25) -> 466.6 | E37: =SUM(E23,E24,E25) -> 468.8 | F37: =SUM(F23,F24,F25) -> 475.7 | G37: =SUM(G23,G24,G25) -> 475.1 | H37: =SUM(H23,H24,H25) -> 478 | I37: =SUM(I23,I24,I25) -> 482.2 | ... AD37: =SUM(AD23,AD24,AD25) -> 533.6 | AE37: =CORREL($B$5:$AD$5,B37:AD37) -> 0.66962931
A38: Assorted | B38: =SUM(B31,B19) -> 338.4 | C38: =SUM(C31,C19) -> 341.7 | D38: =SUM(D31,D19) -> 341.9 | E38: =SUM(E31,E19) -> 343.2 | F38: =SUM(F31,F19) -> 348.7 | G38: =SUM(G31,G19) -> 348.4 | H38: =SUM(H31,H19) -> 350.2 | I38: =SUM(I31,I19) -> 352.1 | ... AD38: =SUM(AD31,AD19) -> 376.7 | AE38: =CORREL($B$5:$AD$5,B38:AD38) -> 0.62998742
